Workbook

Sheet All Upgrades
A1: Group | B1: Tier | C1: Location | D1: Install # | E1: Version at | F1: Slot type | G1: Upgrade | H1: Effect | I1: Per-install value | J1: Total after install | K1: Cost item | L1: Amount | M1: Capstone rare | N1: Rares | O1: Rate key | P1: Notes | Q1: Package id | R1: Game value | S1: Before install
A2: System | B2: 1 | C2: School | D2: 1 | E2: v0.1 | F2: Track | G2: Cooling | H2: Passive cooling per second | I2: +0.3 C/s | J2: 0.5 C/s cooling | K2: Logs | L2: =MAX(1,ROUND(0.3*Inputs!$B$4*Inputs!$B$5^(B2-1)*INDEX(Inputs!$C$15:$C$23,MATCH("mining",Inputs!$A$15:$A$23,0))*Inputs!$B$7*Inputs!$B$6^(D2-1)/Inputs!$B$12,0)) -> 21 | O2: mining | Q2: system.cooling_amount | R2: 0.3 | S2: 0.2 C/s cooling
A3: System | B3: 1 | C3: School | D3: 2 | E3: v0.2 | F3: Track | G3: Heat Reduction | H3: Less heat from every process (percent of each heat tick) | I3: -5% | J3: 5 % less heat | K3: Logs | L3: =MAX(1,ROUND(0.3*Inputs!$B$4*Inputs!$B$5^(B3-1)*INDEX(Inputs!$C$15:$C$23,MATCH("mining",Inputs!$A$15:$A$23,0))*Inputs!$B$7*Inputs!$B$6^(D3-1)/Inputs!$B$12,0)) -> 24 | O3: mining | Q3: system.heat_reduction | R3: 0.05 | S3: 0 % less heat
A4: System | B4: 1 | C4: School | D4: 3 | E4: v0.3 | F4: Track | G4: VM Windows | H4: Max simultaneous VM windows | I4: +1 | J4: 2 VM windows | K4: VM tokens (any skill) | L4: =MAX(1,ROUND(0.1*Inputs!$B$9*Inputs!$B$10^(B4-1),0)) -> 1 | O4: tokens | Q4: system.vm_windows | R4: 1 | S4: 1 VM windows
A5: System | B5: 1 | C5: School | D5: 4 | E5: v0.4 | F5: Track | G5: Background Services | H5: Offline progression cap: +2 h per install on top of the 1 h base (24 h max) | I5: +2 h | J5: 2 h added to the 1 h offline cap | K5: Logs | L5: =MAX(1,ROUND(0.3*Inputs!$B$4*Inputs!$B$5^(B5-1)*INDEX(Inputs!$C$15:$C$23,MATCH("mining",Inputs!$A$15:$A$23,0))*Inputs!$B$7*Inputs!$B$6^(D5-1)/Inputs!$B$12,0)) -> 32 | O5: mining | Q5: system.background_services | R5: 2 | S5: 0 h added to the 1 h offline cap
A6: System | B6: 1 | C6: School | D6: 5 | E6: v0.5 | F6: Track | G6: Background Services | H6: Offline progression cap | I6: +2 h | J6: 4 h added to the 1 h offline cap | K6: Logs | L6: =MAX(1,ROUND(0.3*Inputs!$B$4*Inputs!$B$5^(B6-1)*INDEX(Inputs!$C$15:$C$23,MATCH("mining",Inputs!$A$15:$A$23,0))*Inputs!$B$7*Inputs!$B$6^(D6-1)/Inputs!$B$12,0)) -> 37 | O6: mining | Q6: system.background_services | R6: 2 | S6: 2 h added to the 1 h offline cap
A7: System | B7: 1 | C7: School | D7: 6 | E7: v0.6 | F7: Track | G7: Defrag Duration | H7: Defrag boosts last longer | I7: +2.5 min | J7: 12.5 min boost | K7: Logs | L7: =MAX(1,ROUND(0.3*Inputs!$B$4*Inputs!$B$5^(B7-1)*INDEX(Inputs!$C$15:$C$23,MATCH("mining",Inputs!$A$15:$A$23,0))*Inputs!$B$7*Inputs!$B$6^(D7-1)/Inputs!$B$12,0)) -> 42 | O7: mining | Q7: system.defrag_duration | R7: 2.5 | S7: 10 min boost
A8: System | B8: 1 | C8: School | D8: 7 | E8: v0.7 | F8: Track | G8: Defrag Cooldown | H8: Shared defrag cooldown shorter (meets duration at max) | I8: -2.5 min | J8: 37.5 min cooldown | K8: Logs | L8: =MAX(1,ROUND(0.3*Inputs!$B$4*Inputs!$B$5^(B8-1)*INDEX(Inputs!$C$15:$C$23,MATCH("mining",Inputs!$A$15:$A$23,0))*Inputs!$B$7*Inputs!$B$6^(D8-1)/Inputs!$B$12,0)) -> 49 | O8: mining | Q8: system.defrag_cooldown | R8: 2.5 | S8: 40 min cooldown
A9: System | B9: 1 | C9: School | D9: 8 | E9: v0.8 | F9: Pointed | G9: VM Snapshot | H9: Chance a VM token isn't used up when a VM starts or renews (5% at Tier 1, +3% per tier) | I9: +5% / +3% | J9: 5 % chance to keep the VM token | K9: Logs | L9: =MAX(1,ROUND(0.3*Inputs!$B$4*Inputs!$B$5^(B9-1)*INDEX(Inputs!$C$15:$C$23,MATCH("mining",Inputs!$A$15:$A$23,0))*Inputs!$B$7*Inputs!$B$6^(D9-1)/Inputs!$B$12,0)) -> 56 | O9: mining | Q9: system.vm_snapshot | R9: 0.05 | S9: 0 % chance to keep the VM token
A10: System | B10: 1 | C10: School | D10: 9 | E10: v0.9 | F10: Pointed | G10: Scheduler | H10: VM tokens last longer per use | I10: +10% VM uptime | J10: 10 % VM uptime | K10: VM tokens (any skill) | L10: =MAX(1,ROUND(0.1*Inputs!$B$9*Inputs!$B$10^(B10-1),0)) -> 1 | O10: tokens | Q10: system.scheduler | R10: 0.1 | S10: 0 % VM uptime
A11: System | B11: 1 | C11: School | D11: 10 | E11: v1.0 | F11: Capstone | G11: MAJOR: Overheat Fan | H11: +0.3 C/s cooling while overheated (existing upgrade, kept) | I11: one-off | K11: Logs | L11: =MAX(1,ROUND(0.3*Inputs!$B$4*Inputs!$B$5^(B11-1)*INDEX(Inputs!$C$15:$C$23,MATCH("mining",Inputs!$A$15:$A$23,0))*Inputs!$B$7*Inputs!$B$6^(D11-1)/Inputs!$B$12,0)) -> 74 | M11: Parents credit card | N11: 1 | O11: mining | Q11: system.overheat_fan | R11: =TRUE() -> TRUE | S11: not installed
A12: System | B12: 2 | C12: Lawfirm | D12: 1 | E12: v1.1 | F12: Track | G12: Cooling | H12: Passive cooling per second | I12: +0.35 C/s | J12: 0.85 C/s cooling | K12: Archives | L12: =MAX(1,ROUND(0.7*Inputs!$B$4*Inputs!$B$5^(B12-1)*INDEX(Inputs!$C$15:$C$23,MATCH("mining",Inputs!$A$15:$A$23,0))*Inputs!$B$7*Inputs!$B$6^(D12-1)/Inputs!$B$12,0)) -> 54 | O12: mining | Q12: system.cooling_amount | R12: 0.35 | S12: 0.5 C/s cooling
A13: System | B13: 2 | C13: Lawfirm | D13: 2 | E13: v1.2 | F13: Track | G13: Heat Reduction | H13: Less heat from every process (percent of each heat tick) | I13: -5% | J13: 10 % less heat | K13: Archives | L13: =MAX(1,ROUND(0.7*Inputs!$B$4*Inputs!$B$5^(B13-1)*INDEX(Inputs!$C$15:$C$23,MATCH("mining",Inputs!$A$15:$A$23,0))*Inputs!$B$7*Inputs!$B$6^(D13-1)/Inputs!$B$12,0)) -> 62 | O13: mining | Q13: system.heat_reduction | R13: 0.05 | S13: 5 % less heat
A14: System | B14: 2 | C14: Lawfirm | D14: 3 | E14: v1.3 | F14: Track | G14: VM Windows | H14: Max simultaneous VM windows | I14: +1 | J14: 3 VM windows | K14: VM tokens (any skill) | L14: =MAX(1,ROUND(0.7*Inputs!$B$9*Inputs!$B$10^(B14-1),0)) -> 11 | O14: tokens | Q14: system.vm_windows | R14: 1 | S14: 2 VM windows
A15: System | B15: 2 | C15: Lawfirm | D15: 4 | E15: v1.4 | F15: Track | G15: Background Services | H15: Offline progression cap: +2 h per install on top of the 1 h base (24 h max) | I15: +2 h | J15: 6 h added to the 1 h offline cap | K15: Archives | L15: =MAX(1,ROUND(0.7*Inputs!$B$4*Inputs!$B$5^(B15-1)*INDEX(Inputs!$C$15:$C$23,MATCH("mining",Inputs!$A$15:$A$23,0))*Inputs!$B$7*Inputs!$B$6^(D15-1)/Inputs!$B$12,0)) -> 82 | O15: mining | Q15: system.background_services | R15: 2 | S15: 4 h added to the 1 h offline cap
A16: System | B16: 2 | C16: Lawfirm | D16: 5 | E16: v1.5 | F16: Track | G16: Background Services | H16: Offline progression cap | I16: +2 h | J16: 8 h added to the 1 h offline cap | K16: Archives | L16: =MAX(1,ROUND(0.7*Inputs!$B$4*Inputs!$B$5^(B16-1)*INDEX(Inputs!$C$15:$C$23,MATCH("mining",Inputs!$A$15:$A$23,0))*Inputs!$B$7*Inputs!$B$6^(D16-1)/Inputs!$B$12,0)) -> 95 | O16: mining | Q16: system.background_services | R16: 2 | S16: 6 h added to the 1 h offline cap
A17: System | B17: 2 | C17: Lawfirm | D17: 6 | E17: v1.6 | F17: Track | G17: Defrag Duration | H17: Defrag boosts last longer | I17: +2.5 min | J17: 15 min boost | K17: Archives | L17: =MAX(1,ROUND(0.7*Inputs!$B$4*Inputs!$B$5^(B17-1)*INDEX(Inputs!$C$15:$C$23,MATCH("mining",Inputs!$A$15:$A$23,0))*Inputs!$B$7*Inputs!$B$6^(D17-1)/Inputs!$B$12,0)) -> 109 | O17: mining | Q17: system.defrag_duration | R17: 2.5 | S17: 12.5 min boost
A18: System | B18: 2 | C18: Lawfirm | D18: 7 | E18: v1.7 | F18: Track | G18: Defrag Cooldown | H18: Shared defrag cooldown shorter (meets duration at max) | I18: -2.5 min | J18: 35 min cooldown | K18: Archives | L18: =MAX(1,ROUND(0.7*Inputs!$B$4*Inputs!$B$5^(B18-1)*INDEX(Inputs!$C$15:$C$23,MATCH("mining",Inputs!$A$15:$A$23,0))*Inputs!$B$7*Inputs!$B$6^(D18-1)/Inputs!$B$12,0)) -> 125 | O18: mining | Q18: system.defrag_cooldown | R18: 2.5 | S18: 37.5 min cooldown
A19: System | B19: 2 | C19: Lawfirm | D19: 8 | E19: v1.8 | F19: Pointed | G19: VM Snapshot | H19: Chance a VM token isn't used up when a VM starts or renews (5% at Tier 1, +3% per tier) | I19: +5% / +3% | J19: 8 % chance to keep the VM token | K19: Archives | L19: =MAX(1,ROUND(0.7*Inputs!$B$4*Inputs!$B$5^(B19-1)*INDEX(Inputs!$C$15:$C$23,MATCH("mining",Inputs!$A$15:$A$23,0))*Inputs!$B$7*Inputs!$B$6^(D19-1)/Inputs!$B$12,0)) -> 144 | O19: mining | Q19: system.vm_snapshot | R19: 0.03 | S19: 5 % chance to keep the VM token
A20: System | B20: 2 | C20: Lawfirm | D20: 9 | E20: v1.9 | F20: Pointed | G20: Scheduler | H20: VM tokens last longer per use | I20: +10% VM uptime | J20: 20 % VM uptime | K20: VM tokens (any skill) | L20: =MAX(1,ROUND(0.7*Inputs!$B$9*Inputs!$B$10^(B20-1),0)) -> 11 | O20: tokens | Q20: system.scheduler | R20: 0.1 | S20: 10 % VM uptime
A21: System | B21: 2 | C21: Lawfirm | D21: 10 | E21: v2.0 | F21: Capstone | G21: MAJOR: Idle Cooling | H21: Cooling x2 while no process is running | I21: one-off | K21: Archives | L21: =MAX(1,ROUND(0.7*Inputs!$B$4*Inputs!$B$5^(B21-1)*INDEX(Inputs!$C$15:$C$23,MATCH("mining",Inputs!$A$15:$A$23,0))*Inputs!$B$7*Inputs!$B$6^(D21-1)/Inputs!$B$12,0)) -> 190 | M21: Leaked deposition transcripts | N21: 1 | O21: mining | Q21: system.idle_cooling | R21: =TRUE() -> TRUE | S21: not installed
A22: System | B22: 3 | C22: Hospital | D22: 1 | E22: v2.1 | F22: Track | G22: Cooling | H22: Passive cooling per second | I22: +0.55 C/s | J22: 1.4 C/s cooling | K22: Metadata | L22: =MAX(1,ROUND(0.85*Inputs!$B$4*Inputs!$B$5^(B22-1)*INDEX(Inputs!$C$15:$C$23,MATCH("mining",Inputs!$A$15:$A$23,0))*Inputs!$B$7*Inputs!$B$6^(D22-1)/Inputs!$B$12,0)) -> 72 | O22: mining | Q22: system.cooling_amount | R22: 0.55 | S22: 0.85 C/s cooling
A23: System | B23: 3 | C23: Hospital | D23: 2 | E23: v2.2 | F23: Track | G23: Heat Reduction | H23: Less heat from every process (percent of each heat tick) | I23: -5% | J23: 15 % less heat | K23: Metadata | L23: =MAX(1,ROUND(0.85*Inputs!$B$4*Inputs!$B$5^(B23-1)*INDEX(Inputs!$C$15:$C$23,MATCH("mining",Inputs!$A$15:$A$23,0))*Inputs!$B$7*Inputs!$B$6^(D23-1)/Inputs!$B$12,0)) -> 83 | O23: mining | Q23: system.heat_reduction | R23: 0.05 | S23: 10 % less heat
A24: System | B24: 3 | C24: Hospital | D24: 3 | E24: v2.3 | F24: Track | G24: VM Windows | H24: Max simultaneous VM windows | I24: +1 | J24: 4 VM windows | K24: VM tokens (any skill) | L24: =MAX(1,ROUND(0.85*Inputs!$B$9*Inputs!$B$10^(B24-1),0)) -> 19 | O24: tokens | Q24: system.vm_windows | R24: 1 | S24: 3 VM windows
A25: System | B25: 3 | C25: Hospital | D25: 4 | E25: v2.4 | F25: Track | G25: Background Services | H25: Offline progression cap: +2 h per install on top of the 1 h base (24 h max) | I25: +2 h | J25: 10 h added to the 1 h offline cap | K25: Metadata | L25: =MAX(1,ROUND(0.85*Inputs!$B$4*Inputs!$B$5^(B25-1)*INDEX(Inputs!$C$15:$C$23,MATCH("mining",Inputs!$A$15:$A$23,0))*Inputs!$B$7*Inputs!$B$6^(D25-1)/Inputs!$B$12,0)) -> 110 | O25: mining | Q25: system.background_services | R25: 2 | S25: 8 h added to the 1 h offline cap
A26: System | B26: 3 | C26: Hospital | D26: 5 | E26: v2.5 | F26: Track | G26: Background Services | H26: Offline progression cap | I26: +2 h | J26: 12 h added to the 1 h offline cap | K26: Metadata | L26: =MAX(1,ROUND(0.85*Inputs!$B$4*Inputs!$B$5^(B26-1)*INDEX(Inputs!$C$15:$C$23,MATCH("mining",Inputs!$A$15:$A$23,0))*Inputs!$B$7*Inputs!$B$6^(D26-1)/Inputs!$B$12,0)) -> 126 | O26: mining | Q26: system.background_services | R26: 2 | S26: 10 h added to the 1 h offline cap
A27: System | B27: 3 | C27: Hospital | D27: 6 | E27: v2.6 | F27: Track | G27: Defrag Duration | H27: Defrag boosts last longer | I27: +2.5 min | J27: 17.5 min boost | K27: Metadata | L27: =MAX(1,ROUND(0.85*Inputs!$B$4*Inputs!$B$5^(B27-1)*INDEX(Inputs!$C$15:$C$23,MATCH("mining",Inputs!$A$15:$A$23,0))*Inputs!$B$7*Inputs!$B$6^(D27-1)/Inputs!$B$12,0)) -> 145 | O27: mining | Q27: system.defrag_duration | R27: 2.5 | S27: 15 min boost
A28: System | B28: 3 | C28: Hospital | D28: 7 | E28: v2.7 | F28: Track | G28: Defrag Cooldown | H28: Shared defrag cooldown shorter (meets duration at max) | I28: -2.5 min | J28: 32.5 min cooldown | K28: Metadata | L28: =MAX(1,ROUND(0.85*Inputs!$B$4*Inputs!$B$5^(B28-1)*INDEX(Inputs!$C$15:$C$23,MATCH("mining",Inputs!$A$15:$A$23,0))*Inputs!$B$7*Inputs!$B$6^(D28-1)/Inputs!$B$12,0)) -> 167 | O28: mining | Q28: system.defrag_cooldown | R28: 2.5 | S28: 35 min cooldown
A29: System | B29: 3 | C29: Hospital | D29: 8 | E29: v2.8 | F29: Pointed | G29: VM Snapshot | H29: Chance a VM token isn't used up when a VM starts or renews (5% at Tier 1, +3% per tier) | I29: +5% / +3% | J29: 11 % chance to keep the VM token | K29: Metadata | L29: =MAX(1,ROUND(0.85*Inputs!$B$4*Inputs!$B$5^(B29-1)*INDEX(Inputs!$C$15:$C$23,MATCH("mining",Inputs!$A$15:$A$23,0))*Inputs!$B$7*Inputs!$B$6^(D29-1)/Inputs!$B$12,0)) -> 192 | O29: mining | Q29: system.vm_snapshot | R29: 0.03 | S29: 8 % chance to keep the VM token
A30: System | B30: 3 | C30: Hospital | D30: 9 | E30: v2.9 | F30: Pointed | G30: Scheduler | H30: VM tokens last longer per use | I30: +10% VM uptime | J30: 30 % VM uptime | K30: VM tokens (any skill) | L30: =MAX(1,ROUND(0.85*Inputs!$B$9*Inputs!$B$10^(B30-1),0)) -> 19 | O30: tokens | Q30: system.scheduler | R30: 0.1 | S30: 20 % VM uptime
A31: System | B31: 3 | C31: Hospital | D31: 10 | E31: v3.0 | F31: Capstone | G31: MAJOR: Liquid Cooling | H31: Overheat recovery twice as fast | I31: one-off | K31: Metadata | L31: =MAX(1,ROUND(0.85*Inputs!$B$4*Inputs!$B$5^(B31-1)*INDEX(Inputs!$C$15:$C$23,MATCH("mining",Inputs!$A$15:$A$23,0))*Inputs!$B$7*Inputs!$B$6^(D31-1)/Inputs!$B$12,0)) -> 254 | M31: Patient appointment history | N31: 2 | O31: mining | Q31: system.liquid_cooling | R31: =TRUE() -> TRUE | S31: not installed
A32: System | B32: 4 | C32: Bank | D32: 1 | E32: v3.1 | F32: Track | G32: Cooling | H32: Passive cooling per second | I32: +0.7 C/s | J32: 2.1 C/s cooling | K32: Cookies | L32: =MAX(1,ROUND(0.75*Inputs!$B$4*Inputs!$B$5^(B32-1)*INDEX(Inputs!$C$15:$C$23,MATCH("mining",Inputs!$A$15:$A$23,0))*Inputs!$B$7*Inputs!$B$6^(D32-1)/Inputs!$B$12,0)) -> 70 | O32: mining | Q32: system.cooling_amount | R32: 0.7 | S32: 1.4 C/s cooling
A33: System | B33: 4 | C33: Bank | D33: 2 | E33: v3.2 | F33: Track | G33: Heat Reduction | H33: Less heat from every process (percent of each heat tick) | I33: -5% | J33: 20 % less heat | K33: Cookies | L33: =MAX(1,ROUND(0.75*Inputs!$B$4*Inputs!$B$5^(B33-1)*INDEX(Inputs!$C$15:$C$23,MATCH("mining",Inputs!$A$15:$A$23,0))*Inputs!$B$7*Inputs!$B$6^(D33-1)/Inputs!$B$12,0)) -> 81 | O33: mining | Q33: system.heat_reduction | R33: 0.05 | S33: 15 % less heat
A34: System | B34: 4 | C34: Bank | D34: 3 | E34: v3.3 | F34: Track | G34: VM Windows | H34: Max simultaneous VM windows | I34: +1 | J34: 5 VM windows | K34: VM tokens (any skill) | L34: =MAX(1,ROUND(0.75*Inputs!$B$9*Inputs!$B$10^(B34-1),0)) -> 25 | O34: tokens | Q34: system.vm_windows | R34: 1 | S34: 4 VM windows
A35: System | B35: 4 | C35: Bank | D35: 4 | E35: v3.4 | F35: Track | G35: Background Services | H35: Offline progression cap: +2 h per install on top of the 1 h base (24 h max) | I35: +2 h | J35: 14 h added to the 1 h offline cap | K35: Cookies | L35: =MAX(1,ROUND(0.75*Inputs!$B$4*Inputs!$B$5^(B35-1)*INDEX(Inputs!$C$15:$C$23,MATCH("mining",Inputs!$A$15:$A$23,0))*Inputs!$B$7*Inputs!$B$6^(D35-1)/Inputs!$B$12,0)) -> 107 | O35: mining | Q35: system.background_services | R35: 2 | S35: 12 h added to the 1 h offline cap
A36: System | B36: 4 | C36: Bank | D36: 5 | E36: v3.5 | F36: Track | G36: Background Services | H36: Offline progression cap | I36: +2 h | J36: 16 h added to the 1 h offline cap | K36: Cookies | L36: =MAX(1,ROUND(0.75*Inputs!$B$4*Inputs!$B$5^(B36-1)*INDEX(Inputs!$C$15:$C$23,MATCH("mining",Inputs!$A$15:$A$23,0))*Inputs!$B$7*Inputs!$B$6^(D36-1)/Inputs!$B$12,0)) -> 123 | O36: mining | Q36: system.background_services | R36: 2 | S36: 14 h added to the 1 h offline cap
A37: System | B37: 4 | C37: Bank | D37: 6 | E37: v3.6 | F37: Track | G37: Defrag Duration | H37: Defrag boosts last longer | I37: +2.5 min | J37: 20 min boost | K37: Cookies | L37: =MAX(1,ROUND(0.75*Inputs!$B$4*Inputs!$B$5^(B37-1)*INDEX(Inputs!$C$15:$C$23,MATCH("mining",Inputs!$A$15:$A$23,0))*Inputs!$B$7*Inputs!$B$6^(D37-1)/Inputs!$B$12,0)) -> 141 | O37: mining | Q37: system.defrag_duration | R37: 2.5 | S37: 17.5 min boost
A38: System | B38: 4 | C38: Bank | D38: 7 | E38: v3.7 | F38: Track | G38: Defrag Cooldown | H38: Shared defrag cooldown shorter (meets duration at max) | I38: -2.5 min | J38: 30 min cooldown | K38: Cookies | L38: =MAX(1,ROUND(0.75*Inputs!$B$4*Inputs!$B$5^(B38-1)*INDEX(Inputs!$C$15:$C$23,MATCH("mining",Inputs!$A$15:$A$23,0))*Inputs!$B$7*Inputs!$B$6^(D38-1)/Inputs!$B$12,0)) -> 162 | O38: mining | Q38: system.defrag_cooldown | R38: 2.5 | S38: 32.5 min cooldown
A39: System | B39: 4 | C39: Bank | D39: 8 | E39: v3.8 | F39: Pointed | G39: VM Snapshot | H39: Chance a VM token isn't used up when a VM starts or renews (5% at Tier 1, +3% per tier) | I39: +5% / +3% | J39: 14 % chance to keep the VM token | K39: Cookies | L39: =MAX(1,ROUND(0.75*Inputs!$B$4*Inputs!$B$5^(B39-1)*INDEX(Inputs!$C$15:$C$23,MATCH("mining",Inputs!$A$15:$A$23,0))*Inputs!$B$7*Inputs!$B$6^(D39-1)/Inputs!$B$12,0)) -> 186 | O39: mining | Q39: system.vm_snapshot | R39: 0.03 | S39: 11 % chance to keep the VM token
A40: System | B40: 4 | C40: Bank | D40: 9 | E40: v3.9 | F40: Pointed | G40: Scheduler | H40: VM tokens last longer per use | I40: +10% VM uptime | J40: 40 % VM uptime | K40: VM tokens (any skill) | L40: =MAX(1,ROUND(0.75*Inputs!$B$9*Inputs!$B$10^(B40-1),0)) -> 25 | O40: tokens | Q40: system.scheduler | R40: 0.1 | S40: 30 % VM uptime
A41: System | B41: 4 | C41: Bank | D41: 10 | E41: v4.0 | F41: Capstone | G41: MAJOR: Load Balancer | H41: VM processes produce half heat | I41: one-off | K41: Cookies | L41: =MAX(1,ROUND(0.75*Inputs!$B$4*Inputs!$B$5^(B41-1)*INDEX(Inputs!$C$15:$C$23,MATCH("mining",Inputs!$A$15:$A$23,0))*Inputs!$B$7*Inputs!$B$6^(D41-1)/Inputs!$B$12,0)) -> 246 | M41: Cash Drawer Override Codes | N41: 2 | O41: mining | Q41: system.load_balancer | R41: =TRUE() -> TRUE | S41: not installed
A42: System | B42: 5 | C42: Police | D42: 1 | E42: v4.1 | F42: Track | G42: Cooling | H42: Passive cooling per second | I42: +1.05 C/s | J42: 3.15 C/s cooling | K42: Repositories | L42: =MAX(1,ROUND(0.75*Inputs!$B$4*Inputs!$B$5^(B42-1)*INDEX(Inputs!$C$15:$C$23,MATCH("mining",Inputs!$A$15:$A$23,0))*Inputs!$B$7*Inputs!$B$6^(D42-1)/Inputs!$B$12,0)) -> 77 | O42: mining | Q42: system.cooling_amount | R42: 1.05 | S42: 2.1 C/s cooling
A43: System | B43: 5 | C43: Police | D43: 2 | E43: v4.2 | F43: Track | G43: Heat Reduction | H43: Less heat from every process (percent of each heat tick) | I43: -5% | J43: 25 % less heat | K43: Repositories | L43: =MAX(1,ROUND(0.75*Inputs!$B$4*Inputs!$B$5^(B43-1)*INDEX(Inputs!$C$15:$C$23,MATCH("mining",Inputs!$A$15:$A$23,0))*Inputs!$B$7*Inputs!$B$6^(D43-1)/Inputs!$B$12,0)) -> 89 | O43: mining | Q43: system.heat_reduction | R43: 0.05 | S43: 20 % less heat
A44: System | B44: 5 | C44: Police | D44: 3 | E44: v4.3 | F44: Track | G44: VM Windows | H44: Max simultaneous VM windows | I44: +1 | J44: 6 VM windows | K44: VM tokens (any skill) | L44: =MAX(1,ROUND(0.75*Inputs!$B$9*Inputs!$B$10^(B44-1),0)) -> 38 | O44: tokens | Q44: system.vm_windows | R44: 1 | S44: 5 VM windows
A45: System | B45: 5 | C45: Police | D45: 4 | E45: v4.4 | F45: Track | G45: Background Services | H45: Offline progression cap: +2 h per install on top of the 1 h base (24 h max) | I45: +2 h | J45: 18 h added to the 1 h offline cap | K45: Repositories | L45: =MAX(1,ROUND(0.75*Inputs!$B$4*Inputs!$B$5^(B45-1)*INDEX(Inputs!$C$15:$C$23,MATCH("mining",Inputs!$A$15:$A$23,0))*Inputs!$B$7*Inputs!$B$6^(D45-1)/Inputs!$B$12,0)) -> 117 | O45: mining | Q45: system.background_services | R45: 2 | S45: 16 h added to the 1 h offline cap
A46: System | B46: 5 | C46: Police | D46: 5 | E46: v4.5 | F46: Track | G46: Background Services | H46: Offline progression cap | I46: +2 h | J46: 20 h added to the 1 h offline cap | K46: Repositories | L46: =MAX(1,ROUND(0.75*Inputs!$B$4*Inputs!$B$5^(B46-1)*INDEX(Inputs!$C$15:$C$23,MATCH("mining",Inputs!$A$15:$A$23,0))*Inputs!$B$7*Inputs!$B$6^(D46-1)/Inputs!$B$12,0)) -> 135 | O46: mining | Q46: system.background_services | R46: 2 | S46: 18 h added to the 1 h offline cap
A47: System | B47: 5 | C47: Police | D47: 6 | E47: v4.6 | F47: Track | G47: Defrag Duration | H47: Defrag boosts last longer | I47: +2.5 min | J47: 22.5 min boost | K47: Repositories | L47: =MAX(1,ROUND(0.75*Inputs!$B$4*Inputs!$B$5^(B47-1)*INDEX(Inputs!$C$15:$C$23,MATCH("mining",Inputs!$A$15:$A$23,0))*Inputs!$B$7*Inputs!$B$6^(D47-1)/Inputs!$B$12,0)) -> 155 | O47: mining | Q47: system.defrag_duration | R47: 2.5 | S47: 20 min boost
A48: System | B48: 5 | C48: Police | D48: 7 | E48: v4.7 | F48: Track | G48: Defrag Cooldown | H48: Shared defrag cooldown shorter (meets duration at max) | I48: -2.5 min | J48: 27.5 min cooldown | K48: Repositories | L48: =MAX(1,ROUND(0.75*Inputs!$B$4*Inputs!$B$5^(B48-1)*INDEX(Inputs!$C$15:$C$23,MATCH("mining",Inputs!$A$15:$A$23,0))*Inputs!$B$7*Inputs!$B$6^(D48-1)/Inputs!$B$12,0)) -> 178 | O48: mining | Q48: system.defrag_cooldown | R48: 2.5 | S48: 30 min cooldown
A49: System | B49: 5 | C49: Police | D49: 8 | E49: v4.8 | F49: Pointed | G49: VM Snapshot | H49: Chance a VM token isn't used up when a VM starts or renews (5% at Tier 1, +3% per tier) | I49: +5% / +3% | J49: 17 % chance to keep the VM token | K49: Repositories | L49: =MAX(1,ROUND(0.75*Inputs!$B$4*Inputs!$B$5^(B49-1)*INDEX(Inputs!$C$15:$C$23,MATCH("mining",Inputs!$A$15:$A$23,0))*Inputs!$B$7*Inputs!$B$6^(D49-1)/Inputs!$B$12,0)) -> 205 | O49: mining | Q49: system.vm_snapshot | R49: 0.03 | S49: 14 % chance to keep the VM token
A50: System | B50: 5 | C50: Police | D50: 9 | E50: v4.9 | F50: Pointed | G50: Scheduler | H50: VM tokens last longer per use | I50: +10% VM uptime | J50: 50 % VM uptime | K50: VM tokens (any skill) | L50: =MAX(1,ROUND(0.75*Inputs!$B$9*Inputs!$B$10^(B50-1),0)) -> 38 | O50: tokens | Q50: system.scheduler | R50: 0.1 | S50: 40 % VM uptime
A51: System | B51: 5 | C51: Police | D51: 10 | E51: v5.0 | F51: Capstone | G51: MAJOR: Watchdog | H51: Overclock switches off by itself at 90 C so it can't push you into overheat | I51: one-off | K51: Repositories | L51: =MAX(1,ROUND(0.75*Inputs!$B$4*Inputs!$B$5^(B51-1)*INDEX(Inputs!$C$15:$C$23,MATCH("mining",Inputs!$A$15:$A$23,0))*Inputs!$B$7*Inputs!$B$6^(D51-1)/Inputs!$B$12,0)) -> 271 | M51: Internal affairs complaint archive | N51: 2 | O51: mining | Q51: system.watchdog | R51: =TRUE() -> TRUE | S51: not installed
A52: System | B52: 6 | C52: Government | D52: 1 | E52: v5.1 | F52: Track | G52: Cooling | H52: Passive cooling per second | I52: +1.55 C/s | J52: 4.7 C/s cooling | K52: Databases | L52: =MAX(1,ROUND(1*Inputs!$B$4*Inputs!$B$5^(B52-1)*INDEX(Inputs!$C$15:$C$23,MATCH("mining",Inputs!$A$15:$A$23,0))*Inputs!$B$7*Inputs!$B$6^(D52-1)/Inputs!$B$12,0)) -> 113 | O52: mining | Q52: system.cooling_amount | R52: 1.55 | S52: 3.15 C/s cooling
A53: System | B53: 6 | C53: Government | D53: 2 | E53: v5.2 | F53: Track | G53: Heat Reduction | H53: Less heat from every process (percent of each heat tick) | I53: -5% | J53: 30 % less heat | K53: Databases | L53: =MAX(1,ROUND(1*Inputs!$B$4*Inputs!$B$5^(B53-1)*INDEX(Inputs!$C$15:$C$23,MATCH("mining",Inputs!$A$15:$A$23,0))*Inputs!$B$7*Inputs!$B$6^(D53-1)/Inputs!$B$12,0)) -> 130 | O53: mining | Q53: system.heat_reduction | R53: 0.05 | S53: 25 % less heat
A54: System | B54: 6 | C54: Government | D54: 3 | E54: v5.3 | F54: Track | G54: VM Windows | H54: Max simultaneous VM windows | I54: +1 | J54: 7 VM windows | K54: VM tokens (any skill) | L54: =MAX(1,ROUND(1*Inputs!$B$9*Inputs!$B$10^(B54-1),0)) -> 76 | O54: tokens | Q54: system.vm_windows | R54: 1 | S54: 6 VM windows
A55: System | B55: 6 | C55: Government | D55: 4 | E55: v5.4 | F55: Track | G55: Background Services | H55: Offline progression cap: +2 h per install on top of the 1 h base (24 h max) | I55: +2 h | J55: 22 h added to the 1 h offline cap | K55: Databases | L55: =MAX(1,ROUND(1*Inputs!$B$4*Inputs!$B$5^(B55-1)*INDEX(Inputs!$C$15:$C$23,MATCH("mining",Inputs!$A$15:$A$23,0))*Inputs!$B$7*Inputs!$B$6^(D55-1)/Inputs!$B$12,0)) -> 172 | O55: mining | Q55: system.background_services | R55: 2 | S55: 20 h added to the 1 h offline cap
A56: System | B56: 6 | C56: Government | D56: 5 | E56: v5.5 | F56: Track | G56: Background Services | H56: Offline progression cap | I56: +2 h | J56: 24 h added to the 1 h offline cap | K56: Databases | L56: =MAX(1,ROUND(1*Inputs!$B$4*Inputs!$B$5^(B56-1)*INDEX(Inputs!$C$15:$C$23,MATCH("mining",Inputs!$A$15:$A$23,0))*Inputs!$B$7*Inputs!$B$6^(D56-1)/Inputs!$B$12,0)) -> 198 | O56: mining | Q56: system.background_services | R56: 2 | S56: 22 h added to the 1 h offline cap
A57: System | B57: 6 | C57: Government | D57: 6 | E57: v5.6 | F57: Track | G57: Defrag Duration | H57: Defrag boosts last longer | I57: +2.5 min | J57: 25 min boost | K57: Databases | L57: =MAX(1,ROUND(1*Inputs!$B$4*Inputs!$B$5^(B57-1)*INDEX(Inputs!$C$15:$C$23,MATCH("mining",Inputs!$A$15:$A$23,0))*Inputs!$B$7*Inputs!$B$6^(D57-1)/Inputs!$B$12,0)) -> 227 | O57: mining | Q57: system.defrag_duration | R57: 2.5 | S57: 22.5 min boost
A58: System | B58: 6 | C58: Government | D58: 7 | E58: v5.7 | F58: Track | G58: Defrag Cooldown | H58: Shared defrag cooldown shorter (meets duration at max) | I58: -2.5 min | J58: 25 min cooldown | K58: Databases | L58: =MAX(1,ROUND(1*Inputs!$B$4*Inputs!$B$5^(B58-1)*INDEX(Inputs!$C$15:$C$23,MATCH("mining",Inputs!$A$15:$A$23,0))*Inputs!$B$7*Inputs!$B$6^(D58-1)/Inputs!$B$12,0)) -> 261 | O58: mining | Q58: system.defrag_cooldown | R58: 2.5 | S58: 27.5 min cooldown
A59: System | B59: 6 | C59: Government | D59: 8 | E59: v5.8 | F59: Pointed | G59: VM Snapshot | H59: Chance a VM token isn't used up when a VM starts or renews (5% at Tier 1, +3% per tier) | I59: +5% / +3% | J59: 20 % chance to keep the VM token | K59: Databases | L59: =MAX(1,ROUND(1*Inputs!$B$4*Inputs!$B$5^(B59-1)*INDEX(Inputs!$C$15:$C$23,MATCH("mining",Inputs!$A$15:$A$23,0))*Inputs!$B$7*Inputs!$B$6^(D59-1)/Inputs!$B$12,0)) -> 301 | O59: mining | Q59: system.vm_snapshot | R59: 0.03 | S59: 17 % chance to keep the VM token
A60: System | B60: 6 | C60: Government | D60: 9 | E60: v5.9 | F60: Pointed | G60: Scheduler | H60: VM tokens last longer per use | I60: +10% VM uptime | J60: 60 % VM uptime | K60: VM tokens (any skill) | L60: =MAX(1,ROUND(1*Inputs!$B$9*Inputs!$B$10^(B60-1),0)) -> 76 | O60: tokens | Q60: system.scheduler | R60: 0.1 | S60: 50 % VM uptime
A61: System | B61: 6 | C61: Government | D61: 10 | E61: v6.0 | F61: Capstone | G61: MAJOR: Server Rack | H61: VMs produce no heat | I61: one-off | K61: Databases | L61: =MAX(1,ROUND(1*Inputs!$B$4*Inputs!$B$5^(B61-1)*INDEX(Inputs!$C$15:$C$23,MATCH("mining",Inputs!$A$15:$A$23,0))*Inputs!$B$7*Inputs!$B$6^(D61-1)/Inputs!$B$12,0)) -> 398 | M61: Registered Voters Database | N61: 2 | O61: mining | Q61: system.server_rack | R61: =TRUE() -> TRUE | S61: not installed
A62: Mining | B62: 1 | C62: School | D62: 1 | E62: v0.1 | F62: Track | G62: Speed | H62: Mining cycle speed (each install ~14.5% faster than before it) | I62: +16.7% | J62: 1.17 x speed | K62: Logs | L62: =MAX(1,ROUND(0.3*Inputs!$B$4*Inputs!$B$5^(B62-1)*INDEX(Inputs!$C$15:$C$23,MATCH("mining",Inputs!$A$15:$A$23,0))*Inputs!$B$7*Inputs!$B$6^(D62-1)/Inputs!$B$12,0)) -> 21 | O62: mining | Q62: mining.speed | R62: 0.1667 | S62: 1 x speed
A63: Mining | B63: 1 | C63: School | D63: 2 | E63: v0.2 | F63: Track | G63: Speed | H63: Mining cycle speed | I63: +16.7% | J63: 1.33 x speed | K63: Logs | L63: =MAX(1,ROUND(0.3*Inputs!$B$4*Inputs!$B$5^(B63-1)*INDEX(Inputs!$C$15:$C$23,MATCH("mining",Inputs!$A$15:$A$23,0))*Inputs!$B$7*Inputs!$B$6^(D63-1)/Inputs!$B$12,0)) -> 24 | O63: mining | Q63: mining.speed | R63: 0.1667 | S63: 1.17 x speed
A64: Mining | B64: 1 | C64: School | D64: 3 | E64: v0.3 | F64: Track | G64: Speed | H64: Mining cycle speed | I64: +16.7% | J64: 1.5 x speed | K64: Logs | L64: =MAX(1,ROUND(0.3*Inputs!$B$4*Inputs!$B$5^(B64-1)*INDEX(Inputs!$C$15:$C$23,MATCH("mining",Inputs!$A$15:$A$23,0))*Inputs!$B$7*Inputs!$B$6^(D64-1)/Inputs!$B$12,0)) -> 28 | O64: mining | Q64: mining.speed | R64: 0.1667 | S64: 1.33 x speed
A65: Mining | B65: 1 | C65: School | D65: 4 | E65: v0.4 | F65: Track | G65: Efficiency | H65: Extra resources per cycle (on top of level efficiency); +100% at max | I65: +8.33% | J65: 8.33 % bonus efficiency | K65: Logs | L65: =MAX(1,ROUND(0.3*Inputs!$B$4*Inputs!$B$5^(B65-1)*INDEX(Inputs!$C$15:$C$23,MATCH("mining",Inputs!$A$15:$A$23,0))*Inputs!$B$7*Inputs!$B$6^(D65-1)/Inputs!$B$12,0)) -> 32 | O65: mining | Q65: mining.efficiency | R65: 0.083333 | S65: 0 % bonus efficiency
A66: Mining | B66: 1 | C66: School | D66: 5 | E66: v0.5 | F66: Track | G66: Efficiency | H66: Extra resources per cycle | I66: +8.33% | J66: 16.67 % bonus efficiency | K66: Logs | L66: =MAX(1,ROUND(0.3*Inputs!$B$4*Inputs!$B$5^(B66-1)*INDEX(Inputs!$C$15:$C$23,MATCH("mining",Inputs!$A$15:$A$23,0))*Inputs!$B$7*Inputs!$B$6^(D66-1)/Inputs!$B$12,0)) -> 37 | O66: mining | Q66: mining.efficiency | R66: 0.083333 | S66: 8.33 % bonus efficiency
A67: Mining | B67: 1 | C67: School | D67: 6 | E67: v0.6 | F67: Track | G67: Heat Sink | H67: Less heat from Mining (replaces Yield, which outweighed efficiency) | I67: -2% | J67: 2 % less Mining heat | K67: Logs | L67: =MAX(1,ROUND(0.3*Inputs!$B$4*Inputs!$B$5^(B67-1)*INDEX(Inputs!$C$15:$C$23,MATCH("mining",Inputs!$A$15:$A$23,0))*Inputs!$B$7*Inputs!$B$6^(D67-1)/Inputs!$B$12,0)) -> 42 | O67: mining | Q67: mining.heat_sink | R67: 0.02 | S67: 0 % less Mining heat
A68: Mining | B68: 1 | C68: School | D68: 7 | E68: v0.7 | F68: Track | G68: Heat Sink | H68: Less heat from Mining | I68: -2% | J68: 4 % less Mining heat | K68: Logs | L68: =MAX(1,ROUND(0.3*Inputs!$B$4*Inputs!$B$5^(B68-1)*INDEX(Inputs!$C$15:$C$23,MATCH("mining",Inputs!$A$15:$A$23,0))*Inputs!$B$7*Inputs!$B$6^(D68-1)/Inputs!$B$12,0)) -> 49 | O68: mining | Q68: mining.heat_sink | R68: 0.02 | S68: 2 % less Mining heat
A69: Mining | B69: 1 | C69: School | D69: 8 | E69: v0.8 | F69: Pointed | G69: Vein Detection | H69: Every Nth cycle yields double; N shrinks each tier | I69: every 10th -> 5th | J69: double every 10th cycle | K69: Logs | L69: =MAX(1,ROUND(0.3*Inputs!$B$4*Inputs!$B$5^(B69-1)*INDEX(Inputs!$C$15:$C$23,MATCH("mining",Inputs!$A$15:$A$23,0))*Inputs!$B$7*Inputs!$B$6^(D69-1)/Inputs!$B$12,0)) -> 56 | O69: mining | Q69: mining.vein_detection | R69: 1 | S69: off
A70: Mining | B70: 1 | C70: School | D70: 9 | E70: v0.9 | F70: Pointed | G70: Pipelining | H70: A finished cycle starts the next one partly filled | I70: +10% head start | J70: 10 % head start | K70: Logs | L70: =MAX(1,ROUND(0.3*Inputs!$B$4*Inputs!$B$5^(B70-1)*INDEX(Inputs!$C$15:$C$23,MATCH("mining",Inputs!$A$15:$A$23,0))*Inputs!$B$7*Inputs!$B$6^(D70-1)/Inputs!$B$12,0)) -> 64 | O70: mining | Q70: mining.pipelining | R70: 0.1 | S70: 0 % head start
A71: Mining | B71: 1 | C71: School | D71: 10 | E71: v1.0 | F71: Capstone | G71: MAJOR: Overclock | H71: MODIFIER 'overclock': faster, more heat (existing; tutorial step depends on it, so keep it cheap) | I71: one-off | K71: Logs | L71: =MAX(1,ROUND(0.3*Inputs!$B$4*Inputs!$B$5^(B71-1)*INDEX(Inputs!$C$15:$C$23,MATCH("mining",Inputs!$A$15:$A$23,0))*Inputs!$B$7*Inputs!$B$6^(D71-1)/Inputs!$B$12,0)) -> 74 | M71: Falsified transcript database | N71: 1 | O71: mining | Q71: mining.overclock | R71: =TRUE() -> TRUE | S71: not installed
A72: Mining | B72: 2 | C72: Lawfirm | D72: 1 | E72: v1.1 | F72: Track | G72: Speed | H72: Mining cycle speed (each install ~14.5% faster than before it) | I72: +25.0% | J72: 1.75 x speed | K72: Archives | L72: =MAX(1,ROUND(0.7*Inputs!$B$4*Inputs!$B$5^(B72-1)*INDEX(Inputs!$C$15:$C$23,MATCH("mining",Inputs!$A$15:$A$23,0))*Inputs!$B$7*Inputs!$B$6^(D72-1)/Inputs!$B$12,0)) -> 54 | O72: mining | Q72: mining.speed | R72: 0.25 | S72: 1.5 x speed
A73: Mining | B73: 2 | C73: Lawfirm | D73: 2 | E73: v1.2 | F73: Track | G73: Speed | H73: Mining cycle speed | I73: +25.0% | J73: 2.0 x speed | K73: Archives | L73: =MAX(1,ROUND(0.7*Inputs!$B$4*Inputs!$B$5^(B73-1)*INDEX(Inputs!$C$15:$C$23,MATCH("mining",Inputs!$A$15:$A$23,0))*Inputs!$B$7*Inputs!$B$6^(D73-1)/Inputs!$B$12,0)) -> 62 | O73: mining | Q73: mining.speed | R73: 0.25 | S73: 1.75 x speed
A74: Mining | B74: 2 | C74: Lawfirm | D74: 3 | E74: v1.3 | F74: Track | G74: Speed | H74: Mining cycle speed | I74: +25.0% | J74: 2.25 x speed | K74: Archives | L74: =MAX(1,ROUND(0.7*Inputs!$B$4*Inputs!$B$5^(B74-1)*INDEX(Inputs!$C$15:$C$23,MATCH("mining",Inputs!$A$15:$A$23,0))*Inputs!$B$7*Inputs!$B$6^(D74-1)/Inputs!$B$12,0)) -> 71 | O74: mining | Q74: mining.speed | R74: 0.25 | S74: 2.0 x speed
A75: Mining | B75: 2 | C75: Lawfirm | D75: 4 | E75: v1.4 | F75: Track | G75: Efficiency | H75: Extra resources per cycle (on top of level efficiency); +100% at max | I75: +8.33% | J75: 25 % bonus efficiency | K75: Archives | L75: =MAX(1,ROUND(0.7*Inputs!$B$4*Inputs!$B$5^(B75-1)*INDEX(Inputs!$C$15:$C$23,MATCH("mining",Inputs!$A$15:$A$23,0))*Inputs!$B$7*Inputs!$B$6^(D75-1)/Inputs!$B$12,0)) -> 82 | O75: mining | Q75: mining.efficiency | R75: 0.083333 | S75: 16.67 % bonus efficiency
A76: Mining | B76: 2 | C76: Lawfirm | D76: 5 | E76: v1.5 | F76: Track | G76: Efficiency | H76: Extra resources per cycle | I76: +8.33% | J76: 33.33 % bonus efficiency | K76: Archives | L76: =MAX(1,ROUND(0.7*Inputs!$B$4*Inputs!$B$5^(B76-1)*INDEX(Inputs!$C$15:$C$23,MATCH("mining",Inputs!$A$15:$A$23,0))*Inputs!$B$7*Inputs!$B$6^(D76-1)/Inputs!$B$12,0)) -> 95 | O76: mining | Q76: mining.efficiency | R76: 0.083333 | S76: 25 % bonus efficiency
A77: Mining | B77: 2 | C77: Lawfirm | D77: 6 | E77: v1.6 | F77: Track | G77: Heat Sink | H77: Less heat from Mining (replaces Yield, which outweighed efficiency) | I77: -2% | J77: 6 % less Mining heat | K77: Archives | L77: =MAX(1,ROUND(0.7*Inputs!$B$4*Inputs!$B$5^(B77-1)*INDEX(Inputs!$C$15:$C$23,MATCH("mining",Inputs!$A$15:$A$23,0))*Inputs!$B$7*Inputs!$B$6^(D77-1)/Inputs!$B$12,0)) -> 109 | O77: mining | Q77: mining.heat_sink | R77: 0.02 | S77: 4 % less Mining heat
A78: Mining | B78: 2 | C78: Lawfirm | D78: 7 | E78: v1.7 | F78: Track | G78: Heat Sink | H78: Less heat from Mining | I78: -2% | J78: 8 % less Mining heat | K78: Archives | L78: =MAX(1,ROUND(0.7*Inputs!$B$4*Inputs!$B$5^(B78-1)*INDEX(Inputs!$C$15:$C$23,MATCH("mining",Inputs!$A$15:$A$23,0))*Inputs!$B$7*Inputs!$B$6^(D78-1)/Inputs!$B$12,0)) -> 125 | O78: mining | Q78: mining.heat_sink | R78: 0.02 | S78: 6 % less Mining heat
A79: Mining | B79: 2 | C79: Lawfirm | D79: 8 | E79: v1.8 | F79: Pointed | G79: Vein Detection | H79: Every Nth cycle yields double; N shrinks each tier | I79: every 10th -> 5th | J79: double every 9th cycle | K79: Archives | L79: =MAX(1,ROUND(0.7*Inputs!$B$4*Inputs!$B$5^(B79-1)*INDEX(Inputs!$C$15:$C$23,MATCH("mining",Inputs!$A$15:$A$23,0))*Inputs!$B$7*Inputs!$B$6^(D79-1)/Inputs!$B$12,0)) -> 144 | O79: mining | Q79: mining.vein_detection | R79: 1 | S79: double every 10th cycle
A80: Mining | B80: 2 | C80: Lawfirm | D80: 9 | E80: v1.9 | F80: Pointed | G80: Pipelining | H80: A finished cycle starts the next one partly filled | I80: +10% head start | J80: 20 % head start | K80: Archives | L80: =MAX(1,ROUND(0.7*Inputs!$B$4*Inputs!$B$5^(B80-1)*INDEX(Inputs!$C$15:$C$23,MATCH("mining",Inputs!$A$15:$A$23,0))*Inputs!$B$7*Inputs!$B$6^(D80-1)/Inputs!$B$12,0)) -> 165 | O80: mining | Q80: mining.pipelining | R80: 0.1 | S80: 10 % head start
A81: Mining | B81: 2 | C81: Lawfirm | D81: 10 | E81: v2.0 | F81: Capstone | G81: MAJOR: Deep Core | H81: Passive: VM Mining token chance x2 | I81: one-off | K81: Archives | L81: =MAX(1,ROUND(0.7*Inputs!$B$4*Inputs!$B$5^(B81-1)*INDEX(Inputs!$C$15:$C$23,MATCH("mining",Inputs!$A$15:$A$23,0))*Inputs!$B$7*Inputs!$B$6^(D81-1)/Inputs!$B$12,0)) -> 190 | M81: Forged court document templates | N81: 1 | O81: mining | Q81: mining.deep_core | R81: =TRUE() -> TRUE | S81: not installed
A82: Mining | B82: 3 | C82: Hospital | D82: 1 | E82: v2.1 | F82: Track | G82: Speed | H82: Mining cycle speed (each install ~14.5% faster than before it) | I82: +37.5% | J82: 2.63 x speed | K82: Metadata | L82: =MAX(1,ROUND(0.85*Inputs!$B$4*Inputs!$B$5^(B82-1)*INDEX(Inputs!$C$15:$C$23,MATCH("mining",Inputs!$A$15:$A$23,0))*Inputs!$B$7*Inputs!$B$6^(D82-1)/Inputs!$B$12,0)) -> 72 | O82: mining | Q82: mining.speed | R82: 0.375 | S82: 2.25 x speed
A83: Mining | B83: 3 | C83: Hospital | D83: 2 | E83: v2.2 | F83: Track | G83: Speed | H83: Mining cycle speed | I83: +37.5% | J83: 3.0 x speed | K83: Metadata | L83: =MAX(1,ROUND(0.85*Inputs!$B$4*Inputs!$B$5^(B83-1)*INDEX(Inputs!$C$15:$C$23,MATCH("mining",Inputs!$A$15:$A$23,0))*Inputs!$B$7*Inputs!$B$6^(D83-1)/Inputs!$B$12,0)) -> 83 | O83: mining | Q83: mining.speed | R83: 0.375 | S83: 2.63 x speed
A84: Mining | B84: 3 | C84: Hospital | D84: 3 | E84: v2.3 | F84: Track | G84: Speed | H84: Mining cycle speed | I84: +37.5% | J84: 3.38 x speed | K84: Metadata | L84: =MAX(1,ROUND(0.85*Inputs!$B$4*Inputs!$B$5^(B84-1)*INDEX(Inputs!$C$15:$C$23,MATCH("mining",Inputs!$A$15:$A$23,0))*Inputs!$B$7*Inputs!$B$6^(D84-1)/Inputs!$B$12,0)) -> 95 | O84: mining | Q84: mining.speed | R84: 0.375 | S84: 3.0 x speed
A85: Mining | B85: 3 | C85: Hospital | D85: 4 | E85: v2.4 | F85: Track | G85: Efficiency | H85: Extra resources per cycle (on top of level efficiency); +100% at max | I85: +8.33% | J85: 41.67 % bonus efficiency | K85: Metadata | L85: =MAX(1,ROUND(0.85*Inputs!$B$4*Inputs!$B$5^(B85-1)*INDEX(Inputs!$C$15:$C$23,MATCH("mining",Inputs!$A$15:$A$23,0))*Inputs!$B$7*Inputs!$B$6^(D85-1)/Inputs!$B$12,0)) -> 110 | O85: mining | Q85: mining.efficiency | R85: 0.083333 | S85: 33.33 % bonus efficiency
A86: Mining | B86: 3 | C86: Hospital | D86: 5 | E86: v2.5 | F86: Track | G86: Efficiency | H86: Extra resources per cycle | I86: +8.33% | J86: 50 % bonus efficiency | K86: Metadata | L86: =MAX(1,ROUND(0.85*Inputs!$B$4*Inputs!$B$5^(B86-1)*INDEX(Inputs!$C$15:$C$23,MATCH("mining",Inputs!$A$15:$A$23,0))*Inputs!$B$7*Inputs!$B$6^(D86-1)/Inputs!$B$12,0)) -> 126 | O86: mining | Q86: mining.efficiency | R86: 0.083333 | S86: 41.67 % bonus efficiency
A87: Mining | B87: 3 | C87: Hospital | D87: 6 | E87: v2.6 | F87: Track | G87: Heat Sink | H87: Less heat from Mining (replaces Yield, which outweighed efficiency) | I87: -2% | J87: 10 % less Mining heat | K87: Metadata | L87: =MAX(1,ROUND(0.85*Inputs!$B$4*Inputs!$B$5^(B87-1)*INDEX(Inputs!$C$15:$C$23,MATCH("mining",Inputs!$A$15:$A$23,0))*Inputs!$B$7*Inputs!$B$6^(D87-1)/Inputs!$B$12,0)) -> 145 | O87: mining | Q87: mining.heat_sink | R87: 0.02 | S87: 8 % less Mining heat
A88: Mining | B88: 3 | C88: Hospital | D88: 7 | E88: v2.7 | F88: Track | G88: Heat Sink | H88: Less heat from Mining | I88: -2% | J88: 12 % less Mining heat | K88: Metadata | L88: =MAX(1,ROUND(0.85*Inputs!$B$4*Inputs!$B$5^(B88-1)*INDEX(Inputs!$C$15:$C$23,MATCH("mining",Inputs!$A$15:$A$23,0))*Inputs!$B$7*Inputs!$B$6^(D88-1)/Inputs!$B$12,0)) -> 167 | O88: mining | Q88: mining.heat_sink | R88: 0.02 | S88: 10 % less Mining heat
A89: Mining | B89: 3 | C89: Hospital | D89: 8 | E89: v2.8 | F89: Pointed | G89: Vein Detection | H89: Every Nth cycle yields double; N shrinks each tier | I89: every 10th -> 5th | J89: double every 8th cycle | K89: Metadata | L89: =MAX(1,ROUND(0.85*Inputs!$B$4*Inputs!$B$5^(B89-1)*INDEX(Inputs!$C$15:$C$23,MATCH("mining",Inputs!$A$15:$A$23,0))*Inputs!$B$7*Inputs!$B$6^(D89-1)/Inputs!$B$12,0)) -> 192 | O89: mining | Q89: mining.vein_detection | R89: 1 | S89: double every 9th cycle
A90: Mining | B90: 3 | C90: Hospital | D90: 9 | E90: v2.9 | F90: Pointed | G90: Pipelining | H90: A finished cycle starts the next one partly filled | I90: +10% head start | J90: 30 % head start | K90: Metadata | L90: =MAX(1,ROUND(0.85*Inputs!$B$4*Inputs!$B$5^(B90-1)*INDEX(Inputs!$C$15:$C$23,MATCH("mining",Inputs!$A$15:$A$23,0))*Inputs!$B$7*Inputs!$B$6^(D90-1)/Inputs!$B$12,0)) -> 221 | O90: mining | Q90: mining.pipelining | R90: 0.1 | S90: 20 % head start
A91: Mining | B91: 3 | C91: Hospital | D91: 10 | E91: v3.0 | F91: Capstone | G91: MAJOR: Sift | H91: MODIFIER 'sift': -50% speed, heat x1.5; each cycle 15% chance to also find one of the tier's Parsing items | I91: one-off | K91: Metadata | L91: =MAX(1,ROUND(0.85*Inputs!$B$4*Inputs!$B$5^(B91-1)*INDEX(Inputs!$C$15:$C$23,MATCH("mining",Inputs!$A$15:$A$23,0))*Inputs!$B$7*Inputs!$B$6^(D91-1)/Inputs!$B$12,0)) -> 254 | M91: Staff keycard clone data | N91: 2 | O91: mining | Q91: mining.sift | R91: =TRUE() -> TRUE | S91: not installed
A92: Mining | B92: 4 | C92: Bank | D92: 1 | E92: v3.1 | F92: Track | G92: Speed | H92: Mining cycle speed (each install ~14.5% faster than before it) | I92: +56.2% | J92: 3.94 x speed | K92: Cookies | L92: =MAX(1,ROUND(0.75*Inputs!$B$4*Inputs!$B$5^(B92-1)*INDEX(Inputs!$C$15:$C$23,MATCH("mining",Inputs!$A$15:$A$23,0))*Inputs!$B$7*Inputs!$B$6^(D92-1)/Inputs!$B$12,0)) -> 70 | O92: mining | Q92: mining.speed | R92: 0.5625 | S92: 3.38 x speed
A93: Mining | B93: 4 | C93: Bank | D93: 2 | E93: v3.2 | F93: Track | G93: Speed | H93: Mining cycle speed | I93: +56.2% | J93: 4.5 x speed | K93: Cookies | L93: =MAX(1,ROUND(0.75*Inputs!$B$4*Inputs!$B$5^(B93-1)*INDEX(Inputs!$C$15:$C$23,MATCH("mining",Inputs!$A$15:$A$23,0))*Inputs!$B$7*Inputs!$B$6^(D93-1)/Inputs!$B$12,0)) -> 81 | O93: mining | Q93: mining.speed | R93: 0.5625 | S93: 3.94 x speed
A94: Mining | B94: 4 | C94: Bank | D94: 3 | E94: v3.3 | F94: Track | G94: Speed | H94: Mining cycle speed | I94: +56.2% | J94: 5.06 x speed | K94: Cookies | L94: =MAX(1,ROUND(0.75*Inputs!$B$4*Inputs!$B$5^(B94-1)*INDEX(Inputs!$C$15:$C$23,MATCH("mining",Inputs!$A$15:$A$23,0))*Inputs!$B$7*Inputs!$B$6^(D94-1)/Inputs!$B$12,0)) -> 93 | O94: mining | Q94: mining.speed | R94: 0.5625 | S94: 4.5 x speed
A95: Mining | B95: 4 | C95: Bank | D95: 4 | E95: v3.4 | F95: Track | G95: Efficiency | H95: Extra resources per cycle (on top of level efficiency); +100% at max | I95: +8.33% | J95: 58.33 % bonus efficiency | K95: Cookies | L95: =MAX(1,ROUND(0.75*Inputs!$B$4*Inputs!$B$5^(B95-1)*INDEX(Inputs!$C$15:$C$23,MATCH("mining",Inputs!$A$15:$A$23,0))*Inputs!$B$7*Inputs!$B$6^(D95-1)/Inputs!$B$12,0)) -> 107 | O95: mining | Q95: mining.efficiency | R95: 0.083333 | S95: 50 % bonus efficiency
A96: Mining | B96: 4 | C96: Bank | D96: 5 | E96: v3.5 | F96: Track | G96: Efficiency | H96: Extra resources per cycle | I96: +8.33% | J96: 66.67 % bonus efficiency | K96: Cookies | L96: =MAX(1,ROUND(0.75*Inputs!$B$4*Inputs!$B$5^(B96-1)*INDEX(Inputs!$C$15:$C$23,MATCH("mining",Inputs!$A$15:$A$23,0))*Inputs!$B$7*Inputs!$B$6^(D96-1)/Inputs!$B$12,0)) -> 123 | O96: mining | Q96: mining.efficiency | R96: 0.083333 | S96: 58.33 % bonus efficiency
A97: Mining | B97: 4 | C97: Bank | D97: 6 | E97: v3.6 | F97: Track | G97: Heat Sink | H97: Less heat from Mining (replaces Yield, which outweighed efficiency) | I97: -2% | J97: 14 % less Mining heat | K97: Cookies | L97: =MAX(1,ROUND(0.75*Inputs!$B$4*Inputs!$B$5^(B97-1)*INDEX(Inputs!$C$15:$C$23,MATCH("mining",Inputs!$A$15:$A$23,0))*Inputs!$B$7*Inputs!$B$6^(D97-1)/Inputs!$B$12,0)) -> 141 | O97: mining | Q97: mining.heat_sink | R97: 0.02 | S97: 12 % less Mining heat
A98: Mining | B98: 4 | C98: Bank | D98: 7 | E98: v3.7 | F98: Track | G98: Heat Sink | H98: Less heat from Mining | I98: -2% | J98: 16 % less Mining heat | K98: Cookies | L98: =MAX(1,ROUND(0.75*Inputs!$B$4*Inputs!$B$5^(B98-1)*INDEX(Inputs!$C$15:$C$23,MATCH("mining",Inputs!$A$15:$A$23,0))*Inputs!$B$7*Inputs!$B$6^(D98-1)/Inputs!$B$12,0)) -> 162 | O98: mining | Q98: mining.heat_sink | R98: 0.02 | S98: 14 % less Mining heat
A99: Mining | B99: 4 | C99: Bank | D99: 8 | E99: v3.8 | F99: Pointed | G99: Vein Detection | H99: Every Nth cycle yields double; N shrinks each tier | I99: every 10th -> 5th | J99: double every 7th cycle | K99: Cookies | L99: =MAX(1,ROUND(0.75*Inputs!$B$4*Inputs!$B$5^(B99-1)*INDEX(Inputs!$C$15:$C$23,MATCH("mining",Inputs!$A$15:$A$23,0))*Inputs!$B$7*Inputs!$B$6^(D99-1)/Inputs!$B$12,0)) -> 186 | O99: mining | Q99: mining.vein_detection | R99: 1 | S99: double every 8th cycle
A100: Mining | B100: 4 | C100: Bank | D100: 9 | E100: v3.9 | F100: Pointed | G100: Pipelining | H100: A finished cycle starts the next one partly filled | I100: +10% head start | J100: 40 % head start | K100: Cookies | L100: =MAX(1,ROUND(0.75*Inputs!$B$4*Inputs!$B$5^(B100-1)*INDEX(Inputs!$C$15:$C$23,MATCH("mining",Inputs!$A$15:$A$23,0))*Inputs!$B$7*Inputs!$B$6^(D100-1)/Inputs!$B$12,0)) -> 214 | O100: mining | Q100: mining.pipelining | R100: 0.1 | S100: 30 % head start
...

Sheet Inputs
A1: Cost inputs — every Amount in 'All Upgrades' is calculated from this sheet (blue = edit me)
A4: Hours of solo running per skill, per tier (Tier 1) | B4: 2
A5: Tier time growth (each tier takes this much longer) | B5: 1.1
A6: Cost growth per install within a tier | B6: 1.15
A7: In-tier speed factor (avg speed while buying that tier's 3 speed installs) | B7: 1.25
A8: Rare items per capstone | B8: 2
A9: VM tokens for a token install (Tier 1) | B9: 10
A10: VM token cost growth per tier | B10: 1.5
A12: Weight sum of 10 installs (formula) | B12: =(B6^10-1)/(B6-1) -> 20.303718
A14: Rate key | B14: Currency | C14: Items per hour (Tier 1, level 10, no upgrades) | D14: Source
A15: mining | B15: Tier mined item | C15: 570 | D15: Measured: mine -logs, 8s cycles
A16: parsing | B16: Tier address + encrypted + identifier (total) | C16: 930 | D16: Measured: parse -footprint=logs
A17: cracking | B17: Tier cracked item | C17: 375 | D17: Measured: crack -password
A18: matching | B18: Tier matched item | C18: 210 | D18: Measured: match -cred
A19: phishing | B19: SQL Injectors + Packet Spoofs | C19: 330 | D19: Measured L10 spear: 217/h unbaited, 445/h baited (~6.5k Logs/h); ~330/h with bait limited to ~3k Logs/h
A20: decoding | B20: Tier mined item from caches | C20: 4500 | D20: Measured 120 caches/h x ~37.5 Logs per Student cache
A21: compiling | B21: Tier payload | C21: 420 | D21: Measured: compile -school
A22: hacking | B22: Tier's first-target cache | C22: 82 | D22: Student fights ~44s each incl. access (earlier fight logs)
A23: tokens | B23: VM tokens | C23: 0 | D23: Not time-priced: B9 x B10^(tier-1)
A25: How an Amount is priced: hours x tier growth^(tier-1) x items/hour x in-tier speed x install growth^(install-1) / weight sum.
A26: So one skill's 10 installs in a tier cost exactly 'hours x tier growth^(tier-1)' of solo running at that tier's expected speed.
A27: Rates assume each tier's process runs about as fast as Tier 1 did (1.5x slower base, 1.5x faster from the previous tier's speed installs).

Sheet Summary
A1: IdleOS — Upgrade system plan (DRAFT for balancing)
A3: MODEL
A4: • 9 upgrade groups, 6 tiers each, exactly 10 installs per tier.
A5: • Each install = +0.1 version. Finishing a tier lands on a clean x.0 (v1.0 ... v6.0). Start at v0.0.
A6: • A tier's 10 installs unlock when that location unlocks (via the upload goal you already built).
A8: SLOT MIX PER TIER (10)
A9: • ~6-7 Track rows: speed / efficiency / a group stat. Repeat each tier, values scale.
A10: • ~2-3 Pointed rows (blue): change HOW the skill plays, not just a stat. Same concept each tier, scaling.
A11: • 1 Capstone / MAJOR release (gold): the x.0 standout for that tier.
A13: COSTS (draft)
A14: • Track rows cost that tier's basic resource; Pointed rows cost that tier's cache; Capstone adds a tier rare item.
A15: • Amounts scale by tier (x1, x2.2, x4.5, x9, x18, x36) and by install index. Tune freely.
... A121: • Capstones for groups other than Hacking are placeholders ('MAJOR: ...') — name them when you like the mix.

Sheet Max Anonymity
A1: Max anonymity options (edit the blue inputs)
A3: Base anonymity | B3: 100
A4: Per Hacking level | B4: 5
A5: Per tier unlocked (hybrid only) | B5: 100
A7: Tier | B7: Typical Hacking level at tier entry | C7: First target counter dmg | D7: Toughest target counter dmg | E7: Level only: max anon | F7: Hits to trace (first target) | G7: Hybrid: max anon | H7: Hits to trace (first target)
A8: 1 | B8: 1 | C8: 5 | D8: 12 | E8: =$B$3+$B$4*(B8-1) -> 100 | F8: =E8/C8 -> 20 | G8: =$B$3+$B$4*(B8-1)+$B$5*(1-1) -> 100 | H8: =G8/C8 -> 20
A9: 2 | B9: 15 | C9: 10 | D9: 24 | E9: =$B$3+$B$4*(B9-1) -> 170 | F9: =E9/C9 -> 17 | G9: =$B$3+$B$4*(B9-1)+$B$5*(2-1) -> 270 | H9: =G9/C9 -> 27
A10: 3 | B10: 30 | C10: 18 | D10: 42 | E10: =$B$3+$B$4*(B10-1) -> 245 | F10: =E10/C10 -> 13.611111 | G10: =$B$3+$B$4*(B10-1)+$B$5*(3-1) -> 445 | H10: =G10/C10 -> 24.722222
A11: 4 | B11: 45 | C11: 28 | D11: 66 | E11: =$B$3+$B$4*(B11-1) -> 320 | F11: =E11/C11 -> 11.428571 | G11: =$B$3+$B$4*(B11-1)+$B$5*(4-1) -> 620 | H11: =G11/C11 -> 22.142857
A12: 5 | B12: 60 | C12: 40 | D12: 96 | E12: =$B$3+$B$4*(B12-1) -> 395 | F12: =E12/C12 -> 9.875 | G12: =$B$3+$B$4*(B12-1)+$B$5*(5-1) -> 795 | H12: =G12/C12 -> 19.875
A13: 6 | B13: 75 | C13: 60 | D13: 144 | E13: =$B$3+$B$4*(B13-1) -> 470 | F13: =E13/C13 -> 7.8333333 | G13: =$B$3+$B$4*(B13-1)+$B$5*(6-1) -> 970 | H13: =G13/C13 -> 16.166667
A14: max | B14: 99 | C14: 60 | D14: 144 | E14: =$B$3+$B$4*(B14-1) -> 590 | F14: =E14/C14 -> 9.8333333 | G14: =$B$3+$B$4*(B14-1)+$B$5*(6-1) -> 1090 | H14: =G14/C14 -> 18.166667
A16: Hits to trace = max anonymity / the tier's first easy target's counter damage (no damage reduction, no spoofs).
A17: Tier 1 today: 100 / 5 = 20 hits. Hybrid keeps later tiers close to that feel; level-only lets them get steadily deadlier.
A18: Packet Spoof healing is now % of max anonymity (table below), so it follows this curve.
A20: Packet Spoof healing (% of max anonymity)
A21: Base heal % | B21: 0.05
A22: Heal % per tier upgrade | B22: 0.01
A23: Spoof every (s) | B23: 12.5
A24: Counter every (s), first target | B24: 6.25
A26: Tier | B26: Heal % (with that tier's upgrade) | C26: Heal per spoof (hybrid anon) | D26: First target counter dmg | E26: Heal/s | F26: Incoming dmg/s | G26: Sustain ratio (heal / incoming)
A27: 1 | B27: =$B$21+$B$22*1 -> 0.06 | C27: =ROUND(G8*B27,0) -> 6 | D27: =C8 -> 5 | E27: =C27/$B$23 -> 0.48 | F27: =D27/$B$24 -> 0.8 | G27: =E27/F27 -> 0.6
A28: 2 | B28: =$B$21+$B$22*2 -> 0.07 | C28: =ROUND(G9*B28,0) -> 19 | D28: =C9 -> 10 | E28: =C28/$B$23 -> 1.52 | F28: =D28/$B$24 -> 1.6 | G28: =E28/F28 -> 0.95
A29: 3 | B29: =$B$21+$B$22*3 -> 0.08 | C29: =ROUND(G10*B29,0) -> 36 | D29: =C10 -> 18 | E29: =C29/$B$23 -> 2.88 | F29: =D29/$B$24 -> 2.88 | G29: =E29/F29 -> 1
A30: 4 | B30: =$B$21+$B$22*4 -> 0.09 | C30: =ROUND(G11*B30,0) -> 56 | D30: =C11 -> 28 | E30: =C30/$B$23 -> 4.48 | F30: =D30/$B$24 -> 4.48 | G30: =E30/F30 -> 1
A31: 5 | B31: =$B$21+$B$22*5 -> 0.1 | C31: =ROUND(G12*B31,0) -> 80 | D31: =C12 -> 40 | E31: =C31/$B$23 -> 6.4 | F31: =D31/$B$24 -> 6.4 | G31: =E31/F31 -> 1
A32: 6 | B32: =$B$21+$B$22*6 -> 0.11 | C32: =ROUND(G13*B32,0) -> 107 | D32: =C13 -> 60 | E32: =C32/$B$23 -> 8.56 | F32: =D32/$B$24 -> 9.6 | G32: =E32/F32 -> 0.89166667
A34: Sustain ratio 1.0 = spoofs out-heal the tier's weakest target exactly. Today (Tier 1, flat 5): 0.5. Toughest targets hit ~2.4x harder.
A35: Hacking mods (Restore) and Booster Shot stay as they are: mods add flat restore, Booster Shot doubles the whole heal.

Sheet Tier Totals
A1: Group | B1: Tier | C1: Currency (sum of 10 installs) | D1: Hours of solo running it represents | E1: Rares | G1: Hours = currency / (items per hour x in-tier speed). Should equal Inputs!B4 x Inputs!B5^(tier-1).
A2: System | B2: 1 | C2: =SUMIFS('All Upgrades'!$L$2:$L$541,'All Upgrades'!$A$2:$A$541,A2,'All Upgrades'!$B$2:$B$541,B2,'All Upgrades'!$O$2:$O$541,"<>tokens") -> 335 | D2: =C2/INDEX(Inputs!$C$15:$C$23,MATCH("mining",Inputs!$A$15:$A$23,0))/Inputs!$B$7 -> 0.47017544 | E2: =SUMIFS('All Upgrades'!$N$2:$N$541,'All Upgrades'!$A$2:$A$541,A2,'All Upgrades'!$B$2:$B$541,B2) -> 1
A3: System | B3: 2 | C3: =SUMIFS('All Upgrades'!$L$2:$L$541,'All Upgrades'!$A$2:$A$541,A3,'All Upgrades'!$B$2:$B$541,B3,'All Upgrades'!$O$2:$O$541,"<>tokens") -> 861 | D3: =C3/INDEX(Inputs!$C$15:$C$23,MATCH("mining",Inputs!$A$15:$A$23,0))/Inputs!$B$7 -> 1.2084211 | E3: =SUMIFS('All Upgrades'!$N$2:$N$541,'All Upgrades'!$A$2:$A$541,A3,'All Upgrades'!$B$2:$B$541,B3) -> 1
A4: System | B4: 3 | C4: =SUMIFS('All Upgrades'!$L$2:$L$541,'All Upgrades'!$A$2:$A$541,A4,'All Upgrades'!$B$2:$B$541,B4,'All Upgrades'!$O$2:$O$541,"<>tokens") -> 1149 | D4: =C4/INDEX(Inputs!$C$15:$C$23,MATCH("mining",Inputs!$A$15:$A$23,0))/Inputs!$B$7 -> 1.6126316 | E4: =SUMIFS('All Upgrades'!$N$2:$N$541,'All Upgrades'!$A$2:$A$541,A4,'All Upgrades'!$B$2:$B$541,B4) -> 2
A5: System | B5: 4 | C5: =SUMIFS('All Upgrades'!$L$2:$L$541,'All Upgrades'!$A$2:$A$541,A5,'All Upgrades'!$B$2:$B$541,B5,'All Upgrades'!$O$2:$O$541,"<>tokens") -> 1116 | D5: =C5/INDEX(Inputs!$C$15:$C$23,MATCH("mining",Inputs!$A$15:$A$23,0))/Inputs!$B$7 -> 1.5663158 | E5: =SUMIFS('All Upgrades'!$N$2:$N$541,'All Upgrades'!$A$2:$A$541,A5,'All Upgrades'!$B$2:$B$541,B5) -> 2
A6: System | B6: 5 | C6: =SUMIFS('All Upgrades'!$L$2:$L$541,'All Upgrades'!$A$2:$A$541,A6,'All Upgrades'!$B$2:$B$541,B6,'All Upgrades'!$O$2:$O$541,"<>tokens") -> 1227 | D6: =C6/INDEX(Inputs!$C$15:$C$23,MATCH("mining",Inputs!$A$15:$A$23,0))/Inputs!$B$7 -> 1.7221053 | E6: =SUMIFS('All Upgrades'!$N$2:$N$541,'All Upgrades'!$A$2:$A$541,A6,'All Upgrades'!$B$2:$B$541,B6) -> 2
A7: System | B7: 6 | C7: =SUMIFS('All Upgrades'!$L$2:$L$541,'All Upgrades'!$A$2:$A$541,A7,'All Upgrades'!$B$2:$B$541,B7,'All Upgrades'!$O$2:$O$541,"<>tokens") -> 1800 | D7: =C7/INDEX(Inputs!$C$15:$C$23,MATCH("mining",Inputs!$A$15:$A$23,0))/Inputs!$B$7 -> 2.5263158 | E7: =SUMIFS('All Upgrades'!$N$2:$N$541,'All Upgrades'!$A$2:$A$541,A7,'All Upgrades'!$B$2:$B$541,B7) -> 2
A8: Mining | B8: 1 | C8: =SUMIFS('All Upgrades'!$L$2:$L$541,'All Upgrades'!$A$2:$A$541,A8,'All Upgrades'!$B$2:$B$541,B8,'All Upgrades'!$O$2:$O$541,"<>tokens") -> 427 | D8: =C8/INDEX(Inputs!$C$15:$C$23,MATCH("mining",Inputs!$A$15:$A$23,0))/Inputs!$B$7 -> 0.59929825 | E8: =SUMIFS('All Upgrades'!$N$2:$N$541,'All Upgrades'!$A$2:$A$541,A8,'All Upgrades'!$B$2:$B$541,B8) -> 1
A9: Mining | B9: 2 | C9: =SUMIFS('All Upgrades'!$L$2:$L$541,'All Upgrades'!$A$2:$A$541,A9,'All Upgrades'!$B$2:$B$541,B9,'All Upgrades'!$O$2:$O$541,"<>tokens") -> 1097 | D9: =C9/INDEX(Inputs!$C$15:$C$23,MATCH("mining",Inputs!$A$15:$A$23,0))/Inputs!$B$7 -> 1.5396491 | E9: =SUMIFS('All Upgrades'!$N$2:$N$541,'All Upgrades'!$A$2:$A$541,A9,'All Upgrades'!$B$2:$B$541,B9) -> 1
A10: Mining | B10: 3 | C10: =SUMIFS('All Upgrades'!$L$2:$L$541,'All Upgrades'!$A$2:$A$541,A10,'All Upgrades'!$B$2:$B$541,B10,'All Upgrades'!$O$2:$O$541,"<>tokens") -> 1465 | D10: =C10/INDEX(Inputs!$C$15:$C$23,MATCH("mining",Inputs!$A$15:$A$23,0))/Inputs!$B$7 -> 2.0561404 | E10: =SUMIFS('All Upgrades'!$N$2:$N$541,'All Upgrades'!$A$2:$A$541,A10,'All Upgrades'!$B$2:$B$541,B10) -> 2
A11: Mining | B11: 4 | C11: =SUMIFS('All Upgrades'!$L$2:$L$541,'All Upgrades'!$A$2:$A$541,A11,'All Upgrades'!$B$2:$B$541,B11,'All Upgrades'!$O$2:$O$541,"<>tokens") -> 1423 | D11: =C11/INDEX(Inputs!$C$15:$C$23,MATCH("mining",Inputs!$A$15:$A$23,0))/Inputs!$B$7 -> 1.997193 | E11: =SUMIFS('All Upgrades'!$N$2:$N$541,'All Upgrades'!$A$2:$A$541,A11,'All Upgrades'!$B$2:$B$541,B11) -> 2
A12: Mining | B12: 5 | C12: =SUMIFS('All Upgrades'!$L$2:$L$541,'All Upgrades'!$A$2:$A$541,A12,'All Upgrades'!$B$2:$B$541,B12,'All Upgrades'!$O$2:$O$541,"<>tokens") -> 1565 | D12: =C12/INDEX(Inputs!$C$15:$C$23,MATCH("mining",Inputs!$A$15:$A$23,0))/Inputs!$B$7 -> 2.1964912 | E12: =SUMIFS('All Upgrades'!$N$2:$N$541,'All Upgrades'!$A$2:$A$541,A12,'All Upgrades'!$B$2:$B$541,B12) -> 2
A13: Mining | B13: 6 | C13: =SUMIFS('All Upgrades'!$L$2:$L$541,'All Upgrades'!$A$2:$A$541,A13,'All Upgrades'!$B$2:$B$541,B13,'All Upgrades'!$O$2:$O$541,"<>tokens") -> 2295 | D13: =C13/INDEX(Inputs!$C$15:$C$23,MATCH("mining",Inputs!$A$15:$A$23,0))/Inputs!$B$7 -> 3.2210526 | E13: =SUMIFS('All Upgrades'!$N$2:$N$541,'All Upgrades'!$A$2:$A$541,A13,'All Upgrades'!$B$2:$B$541,B13) -> 2
A14: Parsing | B14: 1 | C14: =SUMIFS('All Upgrades'!$L$2:$L$541,'All Upgrades'!$A$2:$A$541,A14,'All Upgrades'!$B$2:$B$541,B14,'All Upgrades'!$O$2:$O$541,"<>tokens") -> 230 | D14: =C14*3/INDEX(Inputs!$C$15:$C$23,MATCH("parsing",Inputs!$A$15:$A$23,0))/Inputs!$B$7 -> 0.59354839 | E14: =SUMIFS('All Upgrades'!$N$2:$N$541,'All Upgrades'!$A$2:$A$541,A14,'All Upgrades'!$B$2:$B$541,B14) -> 1
A15: Parsing | B15: 2 | C15: =SUMIFS('All Upgrades'!$L$2:$L$541,'All Upgrades'!$A$2:$A$541,A15,'All Upgrades'!$B$2:$B$541,B15,'All Upgrades'!$O$2:$O$541,"<>tokens") -> 596 | D15: =C15*3/INDEX(Inputs!$C$15:$C$23,MATCH("parsing",Inputs!$A$15:$A$23,0))/Inputs!$B$7 -> 1.5380645 | E15: =SUMIFS('All Upgrades'!$N$2:$N$541,'All Upgrades'!$A$2:$A$541,A15,'All Upgrades'!$B$2:$B$541,B15) -> 1
A16: Parsing | B16: 3 | C16: =SUMIFS('All Upgrades'!$L$2:$L$541,'All Upgrades'!$A$2:$A$541,A16,'All Upgrades'!$B$2:$B$541,B16,'All Upgrades'!$O$2:$O$541,"<>tokens") -> 797 | D16: =C16*3/INDEX(Inputs!$C$15:$C$23,MATCH("parsing",Inputs!$A$15:$A$23,0))/Inputs!$B$7 -> 2.0567742 | E16: =SUMIFS('All Upgrades'!$N$2:$N$541,'All Upgrades'!$A$2:$A$541,A16,'All Upgrades'!$B$2:$B$541,B16) -> 2
A17: Parsing | B17: 4 | C17: =SUMIFS('All Upgrades'!$L$2:$L$541,'All Upgrades'!$A$2:$A$541,A17,'All Upgrades'!$B$2:$B$541,B17,'All Upgrades'!$O$2:$O$541,"<>tokens") -> 774 | D17: =C17*3/INDEX(Inputs!$C$15:$C$23,MATCH("parsing",Inputs!$A$15:$A$23,0))/Inputs!$B$7 -> 1.9974194 | E17: =SUMIFS('All Upgrades'!$N$2:$N$541,'All Upgrades'!$A$2:$A$541,A17,'All Upgrades'!$B$2:$B$541,B17) -> 2
A18: Parsing | B18: 5 | C18: =SUMIFS('All Upgrades'!$L$2:$L$541,'All Upgrades'!$A$2:$A$541,A18,'All Upgrades'!$B$2:$B$541,B18,'All Upgrades'!$O$2:$O$541,"<>tokens") -> 849 | D18: =C18*3/INDEX(Inputs!$C$15:$C$23,MATCH("parsing",Inputs!$A$15:$A$23,0))/Inputs!$B$7 -> 2.1909677 | E18: =SUMIFS('All Upgrades'!$N$2:$N$541,'All Upgrades'!$A$2:$A$541,A18,'All Upgrades'!$B$2:$B$541,B18) -> 2
A19: Parsing | B19: 6 | C19: =SUMIFS('All Upgrades'!$L$2:$L$541,'All Upgrades'!$A$2:$A$541,A19,'All Upgrades'!$B$2:$B$541,B19,'All Upgrades'!$O$2:$O$541,"<>tokens") -> 1248 | D19: =C19*3/INDEX(Inputs!$C$15:$C$23,MATCH("parsing",Inputs!$A$15:$A$23,0))/Inputs!$B$7 -> 3.2206452 | E19: =SUMIFS('All Upgrades'!$N$2:$N$541,'All Upgrades'!$A$2:$A$541,A19,'All Upgrades'!$B$2:$B$541,B19) -> 2
A20: Cracking | B20: 1 | C20: =SUMIFS('All Upgrades'!$L$2:$L$541,'All Upgrades'!$A$2:$A$541,A20,'All Upgrades'!$B$2:$B$541,B20,'All Upgrades'!$O$2:$O$541,"<>tokens") -> 281 | D20: =C20/INDEX(Inputs!$C$15:$C$23,MATCH("cracking",Inputs!$A$15:$A$23,0))/Inputs!$B$7 -> 0.59946667 | E20: =SUMIFS('All Upgrades'!$N$2:$N$541,'All Upgrades'!$A$2:$A$541,A20,'All Upgrades'!$B$2:$B$541,B20) -> 1
A21: Cracking | B21: 2 | C21: =SUMIFS('All Upgrades'!$L$2:$L$541,'All Upgrades'!$A$2:$A$541,A21,'All Upgrades'!$B$2:$B$541,B21,'All Upgrades'!$O$2:$O$541,"<>tokens") -> 723 | D21: =C21/INDEX(Inputs!$C$15:$C$23,MATCH("cracking",Inputs!$A$15:$A$23,0))/Inputs!$B$7 -> 1.5424 | E21: =SUMIFS('All Upgrades'!$N$2:$N$541,'All Upgrades'!$A$2:$A$541,A21,'All Upgrades'!$B$2:$B$541,B21) -> 1
A22: Cracking | B22: 3 | C22: =SUMIFS('All Upgrades'!$L$2:$L$541,'All Upgrades'!$A$2:$A$541,A22,'All Upgrades'!$B$2:$B$541,B22,'All Upgrades'!$O$2:$O$541,"<>tokens") -> 964 | D22: =C22/INDEX(Inputs!$C$15:$C$23,MATCH("cracking",Inputs!$A$15:$A$23,0))/Inputs!$B$7 -> 2.0565333 | E22: =SUMIFS('All Upgrades'!$N$2:$N$541,'All Upgrades'!$A$2:$A$541,A22,'All Upgrades'!$B$2:$B$541,B22) -> 2
A23: Cracking | B23: 4 | C23: =SUMIFS('All Upgrades'!$L$2:$L$541,'All Upgrades'!$A$2:$A$541,A23,'All Upgrades'!$B$2:$B$541,B23,'All Upgrades'!$O$2:$O$541,"<>tokens") -> 937 | D23: =C23/INDEX(Inputs!$C$15:$C$23,MATCH("cracking",Inputs!$A$15:$A$23,0))/Inputs!$B$7 -> 1.9989333 | E23: =SUMIFS('All Upgrades'!$N$2:$N$541,'All Upgrades'!$A$2:$A$541,A23,'All Upgrades'!$B$2:$B$541,B23) -> 2
A24: Cracking | B24: 5 | C24: =SUMIFS('All Upgrades'!$L$2:$L$541,'All Upgrades'!$A$2:$A$541,A24,'All Upgrades'!$B$2:$B$541,B24,'All Upgrades'!$O$2:$O$541,"<>tokens") -> 1029 | D24: =C24/INDEX(Inputs!$C$15:$C$23,MATCH("cracking",Inputs!$A$15:$A$23,0))/Inputs!$B$7 -> 2.1952 | E24: =SUMIFS('All Upgrades'!$N$2:$N$541,'All Upgrades'!$A$2:$A$541,A24,'All Upgrades'!$B$2:$B$541,B24) -> 2
A25: Cracking | B25: 6 | C25: =SUMIFS('All Upgrades'!$L$2:$L$541,'All Upgrades'!$A$2:$A$541,A25,'All Upgrades'!$B$2:$B$541,B25,'All Upgrades'!$O$2:$O$541,"<>tokens") -> 1510 | D25: =C25/INDEX(Inputs!$C$15:$C$23,MATCH("cracking",Inputs!$A$15:$A$23,0))/Inputs!$B$7 -> 3.2213333 | E25: =SUMIFS('All Upgrades'!$N$2:$N$541,'All Upgrades'!$A$2:$A$541,A25,'All Upgrades'!$B$2:$B$541,B25) -> 2
A26: Matching | B26: 1 | C26: =SUMIFS('All Upgrades'!$L$2:$L$541,'All Upgrades'!$A$2:$A$541,A26,'All Upgrades'!$B$2:$B$541,B26,'All Upgrades'!$O$2:$O$541,"<>tokens") -> 159 | D26: =C26/INDEX(Inputs!$C$15:$C$23,MATCH("matching",Inputs!$A$15:$A$23,0))/Inputs!$B$7 -> 0.60571429 | E26: =SUMIFS('All Upgrades'!$N$2:$N$541,'All Upgrades'!$A$2:$A$541,A26,'All Upgrades'!$B$2:$B$541,B26) -> 1
A27: Matching | B27: 2 | C27: =SUMIFS('All Upgrades'!$L$2:$L$541,'All Upgrades'!$A$2:$A$541,A27,'All Upgrades'!$B$2:$B$541,B27,'All Upgrades'!$O$2:$O$541,"<>tokens") -> 404 | D27: =C27/INDEX(Inputs!$C$15:$C$23,MATCH("matching",Inputs!$A$15:$A$23,0))/Inputs!$B$7 -> 1.5390476 | E27: =SUMIFS('All Upgrades'!$N$2:$N$541,'All Upgrades'!$A$2:$A$541,A27,'All Upgrades'!$B$2:$B$541,B27) -> 1
A28: Matching | B28: 3 | C28: =SUMIFS('All Upgrades'!$L$2:$L$541,'All Upgrades'!$A$2:$A$541,A28,'All Upgrades'!$B$2:$B$541,B28,'All Upgrades'!$O$2:$O$541,"<>tokens") -> 541 | D28: =C28/INDEX(Inputs!$C$15:$C$23,MATCH("matching",Inputs!$A$15:$A$23,0))/Inputs!$B$7 -> 2.0609524 | E28: =SUMIFS('All Upgrades'!$N$2:$N$541,'All Upgrades'!$A$2:$A$541,A28,'All Upgrades'!$B$2:$B$541,B28) -> 2
A29: Matching | B29: 4 | C29: =SUMIFS('All Upgrades'!$L$2:$L$541,'All Upgrades'!$A$2:$A$541,A29,'All Upgrades'!$B$2:$B$541,B29,'All Upgrades'!$O$2:$O$541,"<>tokens") -> 525 | D29: =C29/INDEX(Inputs!$C$15:$C$23,MATCH("matching",Inputs!$A$15:$A$23,0))/Inputs!$B$7 -> 2 | E29: =SUMIFS('All Upgrades'!$N$2:$N$541,'All Upgrades'!$A$2:$A$541,A29,'All Upgrades'!$B$2:$B$541,B29) -> 2
A30: Matching | B30: 5 | C30: =SUMIFS('All Upgrades'!$L$2:$L$541,'All Upgrades'!$A$2:$A$541,A30,'All Upgrades'!$B$2:$B$541,B30,'All Upgrades'!$O$2:$O$541,"<>tokens") -> 578 | D30: =C30/INDEX(Inputs!$C$15:$C$23,MATCH("matching",Inputs!$A$15:$A$23,0))/Inputs!$B$7 -> 2.2019048 | E30: =SUMIFS('All Upgrades'!$N$2:$N$541,'All Upgrades'!$A$2:$A$541,A30,'All Upgrades'!$B$2:$B$541,B30) -> 2
A31: Matching | B31: 6 | C31: =SUMIFS('All Upgrades'!$L$2:$L$541,'All Upgrades'!$A$2:$A$541,A31,'All Upgrades'!$B$2:$B$541,B31,'All Upgrades'!$O$2:$O$541,"<>tokens") -> 845 | D31: =C31/INDEX(Inputs!$C$15:$C$23,MATCH("matching",Inputs!$A$15:$A$23,0))/Inputs!$B$7 -> 3.2190476 | E31: =SUMIFS('All Upgrades'!$N$2:$N$541,'All Upgrades'!$A$2:$A$541,A31,'All Upgrades'!$B$2:$B$541,B31) -> 2
A32: Phishing | B32: 1 | C32: =SUMIFS('All Upgrades'!$L$2:$L$541,'All Upgrades'!$A$2:$A$541,A32,'All Upgrades'!$B$2:$B$541,B32,'All Upgrades'!$O$2:$O$541,"<>tokens") -> 247 | D32: =C32/INDEX(Inputs!$C$15:$C$23,MATCH("phishing",Inputs!$A$15:$A$23,0))/Inputs!$B$7 -> 0.59878788 | E32: =SUMIFS('All Upgrades'!$N$2:$N$541,'All Upgrades'!$A$2:$A$541,A32,'All Upgrades'!$B$2:$B$541,B32) -> 1
A33: Phishing | B33: 2 | C33: =SUMIFS('All Upgrades'!$L$2:$L$541,'All Upgrades'!$A$2:$A$541,A33,'All Upgrades'!$B$2:$B$541,B33,'All Upgrades'!$O$2:$O$541,"<>tokens") -> 635 | D33: =C33/INDEX(Inputs!$C$15:$C$23,MATCH("phishing",Inputs!$A$15:$A$23,0))/Inputs!$B$7 -> 1.5393939 | E33: =SUMIFS('All Upgrades'!$N$2:$N$541,'All Upgrades'!$A$2:$A$541,A33,'All Upgrades'!$B$2:$B$541,B33) -> 1
A34: Phishing | B34: 3 | C34: =SUMIFS('All Upgrades'!$L$2:$L$541,'All Upgrades'!$A$2:$A$541,A34,'All Upgrades'!$B$2:$B$541,B34,'All Upgrades'!$O$2:$O$541,"<>tokens") -> 849 | D34: =C34/INDEX(Inputs!$C$15:$C$23,MATCH("phishing",Inputs!$A$15:$A$23,0))/Inputs!$B$7 -> 2.0581818 | E34: =SUMIFS('All Upgrades'!$N$2:$N$541,'All Upgrades'!$A$2:$A$541,A34,'All Upgrades'!$B$2:$B$541,B34) -> 2
A35: Phishing | B35: 4 | C35: =SUMIFS('All Upgrades'!$L$2:$L$541,'All Upgrades'!$A$2:$A$541,A35,'All Upgrades'!$B$2:$B$541,B35,'All Upgrades'!$O$2:$O$541,"<>tokens") -> 826 | D35: =C35/INDEX(Inputs!$C$15:$C$23,MATCH("phishing",Inputs!$A$15:$A$23,0))/Inputs!$B$7 -> 2.0024242 | E35: =SUMIFS('All Upgrades'!$N$2:$N$541,'All Upgrades'!$A$2:$A$541,A35,'All Upgrades'!$B$2:$B$541,B35) -> 2
A36: Phishing | B36: 5 | C36: =SUMIFS('All Upgrades'!$L$2:$L$541,'All Upgrades'!$A$2:$A$541,A36,'All Upgrades'!$B$2:$B$541,B36,'All Upgrades'!$O$2:$O$541,"<>tokens") -> 906 | D36: =C36/INDEX(Inputs!$C$15:$C$23,MATCH("phishing",Inputs!$A$15:$A$23,0))/Inputs!$B$7 -> 2.1963636 | E36: =SUMIFS('All Upgrades'!$N$2:$N$541,'All Upgrades'!$A$2:$A$541,A36,'All Upgrades'!$B$2:$B$541,B36) -> 2
A37: Phishing | B37: 6 | C37: =SUMIFS('All Upgrades'!$L$2:$L$541,'All Upgrades'!$A$2:$A$541,A37,'All Upgrades'!$B$2:$B$541,B37,'All Upgrades'!$O$2:$O$541,"<>tokens") -> 1328 | D37: =C37/INDEX(Inputs!$C$15:$C$23,MATCH("phishing",Inputs!$A$15:$A$23,0))/Inputs!$B$7 -> 3.2193939 | E37: =SUMIFS('All Upgrades'!$N$2:$N$541,'All Upgrades'!$A$2:$A$541,A37,'All Upgrades'!$B$2:$B$541,B37) -> 2
A38: Decoding | B38: 1 | C38: =SUMIFS('All Upgrades'!$L$2:$L$541,'All Upgrades'!$A$2:$A$541,A38,'All Upgrades'!$B$2:$B$541,B38,'All Upgrades'!$O$2:$O$541,"<>tokens") -> 3374 | D38: =C38/INDEX(Inputs!$C$15:$C$23,MATCH("decoding",Inputs!$A$15:$A$23,0))/Inputs!$B$7 -> 0.59982222 | E38: =SUMIFS('All Upgrades'!$N$2:$N$541,'All Upgrades'!$A$2:$A$541,A38,'All Upgrades'!$B$2:$B$541,B38) -> 1
A39: Decoding | B39: 2 | C39: =SUMIFS('All Upgrades'!$L$2:$L$541,'All Upgrades'!$A$2:$A$541,A39,'All Upgrades'!$B$2:$B$541,B39,'All Upgrades'!$O$2:$O$541,"<>tokens") -> 8663 | D39: =C39/INDEX(Inputs!$C$15:$C$23,MATCH("decoding",Inputs!$A$15:$A$23,0))/Inputs!$B$7 -> 1.5400889 | E39: =SUMIFS('All Upgrades'!$N$2:$N$541,'All Upgrades'!$A$2:$A$541,A39,'All Upgrades'!$B$2:$B$541,B39) -> 1
A40: Decoding | B40: 3 | C40: =SUMIFS('All Upgrades'!$L$2:$L$541,'All Upgrades'!$A$2:$A$541,A40,'All Upgrades'!$B$2:$B$541,B40,'All Upgrades'!$O$2:$O$541,"<>tokens") -> 11571 | D40: =C40/INDEX(Inputs!$C$15:$C$23,MATCH("decoding",Inputs!$A$15:$A$23,0))/Inputs!$B$7 -> 2.0570667 | E40: =SUMIFS('All Upgrades'!$N$2:$N$541,'All Upgrades'!$A$2:$A$541,A40,'All Upgrades'!$B$2:$B$541,B40) -> 2
A41: Decoding | B41: 4 | C41: =SUMIFS('All Upgrades'!$L$2:$L$541,'All Upgrades'!$A$2:$A$541,A41,'All Upgrades'!$B$2:$B$541,B41,'All Upgrades'!$O$2:$O$541,"<>tokens") -> 11229 | D41: =C41/INDEX(Inputs!$C$15:$C$23,MATCH("decoding",Inputs!$A$15:$A$23,0))/Inputs!$B$7 -> 1.9962667 | E41: =SUMIFS('All Upgrades'!$N$2:$N$541,'All Upgrades'!$A$2:$A$541,A41,'All Upgrades'!$B$2:$B$541,B41) -> 2
A42: Decoding | B42: 5 | C42: =SUMIFS('All Upgrades'!$L$2:$L$541,'All Upgrades'!$A$2:$A$541,A42,'All Upgrades'!$B$2:$B$541,B42,'All Upgrades'!$O$2:$O$541,"<>tokens") -> 12352 | D42: =C42/INDEX(Inputs!$C$15:$C$23,MATCH("decoding",Inputs!$A$15:$A$23,0))/Inputs!$B$7 -> 2.1959111 | E42: =SUMIFS('All Upgrades'!$N$2:$N$541,'All Upgrades'!$A$2:$A$541,A42,'All Upgrades'!$B$2:$B$541,B42) -> 2
A43: Decoding | B43: 6 | C43: =SUMIFS('All Upgrades'!$L$2:$L$541,'All Upgrades'!$A$2:$A$541,A43,'All Upgrades'!$B$2:$B$541,B43,'All Upgrades'!$O$2:$O$541,"<>tokens") -> 18118 | D43: =C43/INDEX(Inputs!$C$15:$C$23,MATCH("decoding",Inputs!$A$15:$A$23,0))/Inputs!$B$7 -> 3.2209778 | E43: =SUMIFS('All Upgrades'!$N$2:$N$541,'All Upgrades'!$A$2:$A$541,A43,'All Upgrades'!$B$2:$B$541,B43) -> 2
A44: Compiling | B44: 1 | C44: =SUMIFS('All Upgrades'!$L$2:$L$541,'All Upgrades'!$A$2:$A$541,A44,'All Upgrades'!$B$2:$B$541,B44,'All Upgrades'!$O$2:$O$541,"<>tokens") -> 316 | D44: =C44/INDEX(Inputs!$C$15:$C$23,MATCH("compiling",Inputs!$A$15:$A$23,0))/Inputs!$B$7 -> 0.60190476 | E44: =SUMIFS('All Upgrades'!$N$2:$N$541,'All Upgrades'!$A$2:$A$541,A44,'All Upgrades'!$B$2:$B$541,B44) -> 1
A45: Compiling | B45: 2 | C45: =SUMIFS('All Upgrades'!$L$2:$L$541,'All Upgrades'!$A$2:$A$541,A45,'All Upgrades'!$B$2:$B$541,B45,'All Upgrades'!$O$2:$O$541,"<>tokens") -> 810 | D45: =C45/INDEX(Inputs!$C$15:$C$23,MATCH("compiling",Inputs!$A$15:$A$23,0))/Inputs!$B$7 -> 1.5428571 | E45: =SUMIFS('All Upgrades'!$N$2:$N$541,'All Upgrades'!$A$2:$A$541,A45,'All Upgrades'!$B$2:$B$541,B45) -> 1
A46: Compiling | B46: 3 | C46: =SUMIFS('All Upgrades'!$L$2:$L$541,'All Upgrades'!$A$2:$A$541,A46,'All Upgrades'!$B$2:$B$541,B46,'All Upgrades'!$O$2:$O$541,"<>tokens") -> 1079 | D46: =C46/INDEX(Inputs!$C$15:$C$23,MATCH("compiling",Inputs!$A$15:$A$23,0))/Inputs!$B$7 -> 2.0552381 | E46: =SUMIFS('All Upgrades'!$N$2:$N$541,'All Upgrades'!$A$2:$A$541,A46,'All Upgrades'!$B$2:$B$541,B46) -> 2
A47: Compiling | B47: 4 | C47: =SUMIFS('All Upgrades'!$L$2:$L$541,'All Upgrades'!$A$2:$A$541,A47,'All Upgrades'!$B$2:$B$541,B47,'All Upgrades'!$O$2:$O$541,"<>tokens") -> 1048 | D47: =C47/INDEX(Inputs!$C$15:$C$23,MATCH("compiling",Inputs!$A$15:$A$23,0))/Inputs!$B$7 -> 1.9961905 | E47: =SUMIFS('All Upgrades'!$N$2:$N$541,'All Upgrades'!$A$2:$A$541,A47,'All Upgrades'!$B$2:$B$541,B47) -> 2
A48: Compiling | B48: 5 | C48: =SUMIFS('All Upgrades'!$L$2:$L$541,'All Upgrades'!$A$2:$A$541,A48,'All Upgrades'!$B$2:$B$541,B48,'All Upgrades'!$O$2:$O$541,"<>tokens") -> 1152 | D48: =C48/INDEX(Inputs!$C$15:$C$23,MATCH("compiling",Inputs!$A$15:$A$23,0))/Inputs!$B$7 -> 2.1942857 | E48: =SUMIFS('All Upgrades'!$N$2:$N$541,'All Upgrades'!$A$2:$A$541,A48,'All Upgrades'!$B$2:$B$541,B48) -> 2
A49: Compiling | B49: 6 | C49: =SUMIFS('All Upgrades'!$L$2:$L$541,'All Upgrades'!$A$2:$A$541,A49,'All Upgrades'!$B$2:$B$541,B49,'All Upgrades'!$O$2:$O$541,"<>tokens") -> 1693 | D49: =C49/INDEX(Inputs!$C$15:$C$23,MATCH("compiling",Inputs!$A$15:$A$23,0))/Inputs!$B$7 -> 3.2247619 | E49: =SUMIFS('All Upgrades'!$N$2:$N$541,'All Upgrades'!$A$2:$A$541,A49,'All Upgrades'!$B$2:$B$541,B49) -> 2
A50: Hacking | B50: 1 | C50: =SUMIFS('All Upgrades'!$L$2:$L$541,'All Upgrades'!$A$2:$A$541,A50,'All Upgrades'!$B$2:$B$541,B50,'All Upgrades'!$O$2:$O$541,"<>tokens") -> 12 | D50: =C50/INDEX(Inputs!$C$15:$C$23,MATCH("hacking",Inputs!$A$15:$A$23,0))/Inputs!$B$7 -> 0.11707317 | E50: =SUMIFS('All Upgrades'!$N$2:$N$541,'All Upgrades'!$A$2:$A$541,A50,'All Upgrades'!$B$2:$B$541,B50) -> 1
A51: Hacking | B51: 2 | C51: =SUMIFS('All Upgrades'!$L$2:$L$541,'All Upgrades'!$A$2:$A$541,A51,'All Upgrades'!$B$2:$B$541,B51,'All Upgrades'!$O$2:$O$541,"<>tokens") -> 15 | D51: =C51/INDEX(Inputs!$C$15:$C$23,MATCH("hacking",Inputs!$A$15:$A$23,0))/Inputs!$B$7 -> 0.14634146 | E51: =SUMIFS('All Upgrades'!$N$2:$N$541,'All Upgrades'!$A$2:$A$541,A51,'All Upgrades'!$B$2:$B$541,B51) -> 1
A52: Hacking | B52: 3 | C52: =SUMIFS('All Upgrades'!$L$2:$L$541,'All Upgrades'!$A$2:$A$541,A52,'All Upgrades'!$B$2:$B$541,B52,'All Upgrades'!$O$2:$O$541,"<>tokens") -> 22 | D52: =C52/INDEX(Inputs!$C$15:$C$23,MATCH("hacking",Inputs!$A$15:$A$23,0))/Inputs!$B$7 -> 0.21463415 | E52: =SUMIFS('All Upgrades'!$N$2:$N$541,'All Upgrades'!$A$2:$A$541,A52,'All Upgrades'!$B$2:$B$541,B52) -> 2
A53: Hacking | B53: 4 | C53: =SUMIFS('All Upgrades'!$L$2:$L$541,'All Upgrades'!$A$2:$A$541,A53,'All Upgrades'!$B$2:$B$541,B53,'All Upgrades'!$O$2:$O$541,"<>tokens") -> 28 | D53: =C53/INDEX(Inputs!$C$15:$C$23,MATCH("hacking",Inputs!$A$15:$A$23,0))/Inputs!$B$7 -> 0.27317073 | E53: =SUMIFS('All Upgrades'!$N$2:$N$541,'All Upgrades'!$A$2:$A$541,A53,'All Upgrades'!$B$2:$B$541,B53) -> 2
A54: Hacking | B54: 5 | C54: =SUMIFS('All Upgrades'!$L$2:$L$541,'All Upgrades'!$A$2:$A$541,A54,'All Upgrades'!$B$2:$B$541,B54,'All Upgrades'!$O$2:$O$541,"<>tokens") -> 34 | D54: =C54/INDEX(Inputs!$C$15:$C$23,MATCH("hacking",Inputs!$A$15:$A$23,0))/Inputs!$B$7 -> 0.33170732 | E54: =SUMIFS('All Upgrades'!$N$2:$N$541,'All Upgrades'!$A$2:$A$541,A54,'All Upgrades'!$B$2:$B$541,B54) -> 2
A55: Hacking | B55: 6 | C55: =SUMIFS('All Upgrades'!$L$2:$L$541,'All Upgrades'!$A$2:$A$541,A55,'All Upgrades'!$B$2:$B$541,B55,'All Upgrades'!$O$2:$O$541,"<>tokens") -> 40 | D55: =C55/INDEX(Inputs!$C$15:$C$23,MATCH("hacking",Inputs!$A$15:$A$23,0))/Inputs!$B$7 -> 0.3902439 | E55: =SUMIFS('All Upgrades'!$N$2:$N$541,'All Upgrades'!$A$2:$A$541,A55,'All Upgrades'!$B$2:$B$541,B55) -> 2

Sheet Rare Demand
A1: Tier | B1: Rare item | C1: Used by capstone of | D1: Capstone need | E1: Upload goal | F1: Total needed | G1: Caches per rare at 4% (L1) | H1: At 8% (L99) | I1: At 12% (max) | K1: Caches columns = caches you'd decode to collect that rare's total need at each rare chance.
A2: 1 | B2: Parents credit card | C2: System, Phishing | D2: =2*Inputs!$B$8 -> 4 | E2: 10 | F2: =D2+E2 -> 14 | G2: =F2/0.04 -> 350 | H2: =F2/0.08 -> 175 | I2: =F2/0.12 -> 116.66667
A3: 1 | B3: Falsified transcript database | C3: Mining, Decoding | D3: =2*Inputs!$B$8 -> 4 | E3: 10 | F3: =D3+E3 -> 14 | G3: =F3/0.04 -> 350 | H3: =F3/0.08 -> 175 | I3: =F3/0.12 -> 116.66667
A4: 1 | B4: Student disciplinary records | C4: Parsing, Compiling | D4: =2*Inputs!$B$8 -> 4 | E4: 10 | F4: =D4+E4 -> 14 | G4: =F4/0.04 -> 350 | H4: =F4/0.08 -> 175 | I4: =F4/0.12 -> 116.66667
A5: 1 | B5: School budget embezzlement logs | C5: Cracking, Hacking | D5: =2*Inputs!$B$8 -> 4 | E5: 10 | F5: =D5+E5 -> 14 | G5: =F5/0.04 -> 350 | H5: =F5/0.08 -> 175 | I5: =F5/0.12 -> 116.66667
A6: 1 | B6: District wide master password | C6: Matching | D6: =1*Inputs!$B$8 -> 2 | E6: 10 | F6: =D6+E6 -> 12 | G6: =F6/0.04 -> 300 | H6: =F6/0.08 -> 150 | I6: =F6/0.12 -> 100
A7: 2 | B7: Leaked deposition transcripts | C7: System, Phishing | D7: =2*Inputs!$B$8 -> 4 | E7: 10 | F7: =D7+E7 -> 14 | G7: =F7/0.04 -> 350 | H7: =F7/0.08 -> 175 | I7: =F7/0.12 -> 116.66667
A8: 2 | B8: Forged court document templates | C8: Mining, Decoding | D8: =2*Inputs!$B$8 -> 4 | E8: 10 | F8: =D8+E8 -> 14 | G8: =F8/0.04 -> 350 | H8: =F8/0.08 -> 175 | I8: =F8/0.12 -> 116.66667
A9: 2 | B9: Sealed case files | C9: Parsing, Compiling | D9: =2*Inputs!$B$8 -> 4 | E9: 10 | F9: =D9+E9 -> 14 | G9: =F9/0.04 -> 350 | H9: =F9/0.08 -> 175 | I9: =F9/0.12 -> 116.66667
A10: 2 | B10: Offshore account records | C10: Cracking, Hacking | D10: =2*Inputs!$B$8 -> 4 | E10: 10 | F10: =D10+E10 -> 14 | G10: =F10/0.04 -> 350 | H10: =F10/0.08 -> 175 | I10: =F10/0.12 -> 116.66667
A11: 2 | B11: Witness protection address | C11: Matching | D11: =1*Inputs!$B$8 -> 2 | E11: 10 | F11: =D11+E11 -> 12 | G11: =F11/0.04 -> 300 | H11: =F11/0.08 -> 150 | I11: =F11/0.12 -> 100
A12: 3 | B12: Patient appointment history | C12: System, Phishing | D12: =2*Inputs!$B$8 -> 4 | E12: 10 | F12: =D12+E12 -> 14 | G12: =F12/0.04 -> 350 | H12: =F12/0.08 -> 175 | I12: =F12/0.12 -> 116.66667
A13: 3 | B13: Staff keycard clone data | C13: Mining, Decoding | D13: =2*Inputs!$B$8 -> 4 | E13: 10 | F13: =D13+E13 -> 14 | G13: =F13/0.04 -> 350 | H13: =F13/0.08 -> 175 | I13: =F13/0.12 -> 116.66667
A14: 3 | B14: Prescription pad credentials | C14: Parsing, Compiling | D14: =2*Inputs!$B$8 -> 4 | E14: 10 | F14: =D14+E14 -> 14 | G14: =F14/0.04 -> 350 | H14: =F14/0.08 -> 175 | I14: =F14/0.12 -> 116.66667
A15: 3 | B15: Patient insurance data | C15: Cracking, Hacking | D15: =2*Inputs!$B$8 -> 4 | E15: 10 | F15: =D15+E15 -> 14 | G15: =F15/0.04 -> 350 | H15: =F15/0.08 -> 175 | I15: =F15/0.12 -> 116.66667
A16: 3 | B16: Falsified drug trial results | C16: Matching | D16: =1*Inputs!$B$8 -> 2 | E16: 10 | F16: =D16+E16 -> 12 | G16: =F16/0.04 -> 300 | H16: =F16/0.08 -> 150 | I16: =F16/0.12 -> 100
A17: 4 | B17: Cash Drawer Override Codes | C17: System, Phishing | D17: =2*Inputs!$B$8 -> 4 | E17: 10 | F17: =D17+E17 -> 14 | G17: =F17/0.04 -> 350 | H17: =F17/0.08 -> 175 | I17: =F17/0.12 -> 116.66667
A18: 4 | B18: Credit Records | C18: Mining, Decoding | D18: =2*Inputs!$B$8 -> 4 | E18: 10 | F18: =D18+E18 -> 14 | G18: =F18/0.04 -> 350 | H18: =F18/0.08 -> 175 | I18: =F18/0.12 -> 116.66667
A19: 4 | B19: Safe Deposit Box Registry | C19: Parsing, Compiling | D19: =2*Inputs!$B$8 -> 4 | E19: 10 | F19: =D19+E19 -> 14 | G19: =F19/0.04 -> 350 | H19: =F19/0.08 -> 175 | I19: =F19/0.12 -> 116.66667
A20: 4 | B20: Vault Override | C20: Cracking, Hacking | D20: =2*Inputs!$B$8 -> 4 | E20: 10 | F20: =D20+E20 -> 14 | G20: =F20/0.04 -> 350 | H20: =F20/0.08 -> 175 | I20: =F20/0.12 -> 116.66667
A21: 4 | B21: Swift Master Key | C21: Matching | D21: =1*Inputs!$B$8 -> 2 | E21: 10 | F21: =D21+E21 -> 12 | G21: =F21/0.04 -> 300 | H21: =F21/0.08 -> 150 | I21: =F21/0.12 -> 100
A22: 5 | B22: Internal affairs complaint archive | C22: System, Phishing | D22: =2*Inputs!$B$8 -> 4 | E22: 10 | F22: =D22+E22 -> 14 | G22: =F22/0.04 -> 350 | H22: =F22/0.08 -> 175 | I22: =F22/0.12 -> 116.66667
A23: 5 | B23: Body cam footage deletion logs | C23: Mining, Decoding | D23: =2*Inputs!$B$8 -> 4 | E23: 10 | F23: =D23+E23 -> 14 | G23: =F23/0.04 -> 350 | H23: =F23/0.08 -> 175 | I23: =F23/0.12 -> 116.66667
A24: 5 | B24: Confidential informant registry | C24: Parsing, Compiling | D24: =2*Inputs!$B$8 -> 4 | E24: 10 | F24: =D24+E24 -> 14 | G24: =F24/0.04 -> 350 | H24: =F24/0.08 -> 175 | I24: =F24/0.12 -> 116.66667
A25: 5 | B25: Evidence locker access codes | C25: Cracking, Hacking | D25: =2*Inputs!$B$8 -> 4 | E25: 10 | F25: =D25+E25 -> 14 | G25: =F25/0.04 -> 350 | H25: =F25/0.08 -> 175 | I25: =F25/0.12 -> 116.66667
A26: 5 | B26: Corruption payout ledger | C26: Matching | D26: =1*Inputs!$B$8 -> 2 | E26: 10 | F26: =D26+E26 -> 12 | G26: =F26/0.04 -> 300 | H26: =F26/0.08 -> 150 | I26: =F26/0.12 -> 100
A27: 6 | B27: Registered Voters Database | C27: System, Phishing | D27: =2*Inputs!$B$8 -> 4 | E27: 10 | F27: =D27+E27 -> 14 | G27: =F27/0.04 -> 350 | H27: =F27/0.08 -> 175 | I27: =F27/0.12 -> 116.66667
A28: 6 | B28: CIA Brief | C28: Mining, Decoding | D28: =2*Inputs!$B$8 -> 4 | E28: 10 | F28: =D28+E28 -> 14 | G28: =F28/0.04 -> 350 | H28: =F28/0.08 -> 175 | I28: =F28/0.12 -> 116.66667
A29: 6 | B29: Black Budget Ledger | C29: Parsing, Compiling | D29: =2*Inputs!$B$8 -> 4 | E29: 10 | F29: =D29+E29 -> 14 | G29: =F29/0.04 -> 350 | H29: =F29/0.08 -> 175 | I29: =F29/0.12 -> 116.66667
A30: 6 | B30: Deep Cover IDs | C30: Cracking, Hacking | D30: =2*Inputs!$B$8 -> 4 | E30: 10 | F30: =D30+E30 -> 14 | G30: =F30/0.04 -> 350 | H30: =F30/0.08 -> 175 | I30: =F30/0.12 -> 116.66667
A31: 6 | B31: Nuclear Codes | C31: Matching | D31: =1*Inputs!$B$8 -> 2 | E31: 10 | F31: =D31+E31 -> 12 | G31: =F31/0.04 -> 300 | H31: =F31/0.08 -> 150 | I31: =F31/0.12 -> 100

Sheet Counts
A1: Group | B1: Installs/tier | C1: Tiers | D1: Total installs | E1: Final version
A2: System | B2: 10 | C2: 6 | D2: 60 | E2: v6.0
A3: Mining | B3: 10 | C3: 6 | D3: 60 | E3: v6.0
A4: Parsing | B4: 10 | C4: 6 | D4: 60 | E4: v6.0
A5: Cracking | B5: 10 | C5: 6 | D5: 60 | E5: v6.0
A6: Matching | B6: 10 | C6: 6 | D6: 60 | E6: v6.0
A7: Phishing | B7: 10 | C7: 6 | D7: 60 | E7: v6.0
A8: Decoding | B8: 10 | C8: 6 | D8: 60 | E8: v6.0
A9: Compiling | B9: 10 | C9: 6 | D9: 60 | E9: v6.0
A10: Hacking | B10: 10 | C10: 6 | D10: 60 | E10: v6.0
A11: TOTAL | B11: 90 | D11: 540
